Workbook
Name BASE: [1]BASE!$D$3:$E$174
Name Print_Area: 'C. a Pagar'!$B$4:$G$7
Name Print_Area: 'C. a Receber'!$B$3:$G$5
Name Print_Area: Pagamentos!$A$2:$E$286
Name Print_Area: Recebimentos!$A$2:$E$5

Sheet Config
C2: GESTÃO FINANCEIRA | M2: 46054
B7: RUBRICAS PARA O DRE | F7: RUBRICAS PARA LISTAGEM SUSPENSA
A8: 1 | B8: RECEITAS BRUTAS | F8: RECEITAS | J8: DESPESAS
A9: 2 | B9: A VISTA (PIX/DEPÓSITO) | F9: *****RECEITAS BRUTAS | J9: *****
A10: 3 | B10: ANTECIPAÇÃO | E10: 2 | F10: =VLOOKUP(E10,$A$8:$D$180,2,0) -> A VISTA (PIX/DEPÓSITO) | I10: 8 | J10: =VLOOKUP(I10,$A$8:$B$182,2,0) -> COFINS
A11: 4 | B11: DESCONTO DUPLICATAS | E11: 3 | F11: =VLOOKUP(E11,$A$8:$D$180,2,0) -> ANTECIPAÇÃO | I11: 9 | J11: =VLOOKUP(I11,$A$8:$B$182,2,0) -> DIFAL
A12: 5 | B12: LIQUIDAÇÃO DE COBRANÇA | E12: 4 | F12: =VLOOKUP(E12,$A$8:$D$180,2,0) -> DESCONTO DUPLICATAS | I12: 10 | J12: =VLOOKUP(I12,$A$8:$B$182,2,0) -> ICMS
A13: 6 | B13: OUTROS | E13: 5 | F13: =VLOOKUP(E13,$A$8:$D$180,2,0) -> LIQUIDAÇÃO DE COBRANÇA | I13: 11 | J13: =VLOOKUP(I13,$A$8:$B$182,2,0) -> IPI
A14: 7 | B14: I.D.R | E14: 6 | F14: =VLOOKUP(E14,$A$8:$D$180,2,0) -> OUTROS | I14: 12 | J14: =VLOOKUP(I14,$A$8:$B$182,2,0) -> ISS
A15: 8 | B15: COFINS | F15: *****RECEITAS NÃO OPERACIONAIS | I15: 13 | J15: =VLOOKUP(I15,$A$8:$B$182,2,0) -> PIS
A16: 9 | B16: DIFAL | E16: 138 | F16: =VLOOKUP(E16,$A$8:$D$180,2,0) -> EMPRÉSTIMOS DIRETORIA REC | I16: 14 | J16: =VLOOKUP(I16,$A$8:$B$182,2,0) -> SIMPLES NACIONAL
A17: 10 | B17: ICMS | E17: 139 | F17: =VLOOKUP(E17,$A$8:$D$180,2,0) -> ESTORNO DE PAGAMENTOS | I17: 15 | J17: =VLOOKUP(I17,$A$8:$B$182,2,0) -> DESÁGIO DESCONTO DUPLICATAS
