Workbook
Name _20_fev_03: #REF!
Name _28_nov_02: #REF!
Name _30_dez_02: #REF!
Name _fl_: [1]DADOS!#REF!
Name BANCO: #REF!
Name BANCO_DADOS: #REF!
Name CC: #REF!
Name CLASSIFICAÇÃO: #REF!
Name dados: #REF!
Name FAVORECIDO: #REF!
Name feriados: [2]Geral!$B$37:$H$50
Name GRUPO: #REF!
Name INST: [3]!Tabela5[INSTITUIÇÃO]
Name INSTITUICAO: OFFSET(PM!$L$13,0,0,'[4]BASE TP OPER'!$R$1)
Name INSTITUICAO: OFFSET(#REF!,0,0,'[4]BASE TP OPER'!$R$1)
Name Instituições: [5]!Tabela8[Instituição]
Name k_desgual: '[2]T Desiguais'!$C$6
Name libio_balboa: #REF!
Name Nao_Uniforme: '[4]NAO UNIFORME'!#REF!,'[4]NAO UNIFORME'!#REF!
Name S_N_U: '[4]NAO UNIFORME'!#REF!
Name SegmentaçãodeDados_BANCO: #N/A
Name SegmentaçãodeDados_BANCO11: #N/A
Name SegmentaçãodeDados_TIPO: #N/A
Name SegmentaçãodeDados_TIPO11: #N/A
Name SNUTI: '[4]NAO UNIFORME'!#REF!
Name SUB_TIPO: #REF!
Name TIPO: #REF!
Name wilma: #REF!

Sheet BASE
A1: PORTADOR | B1: STATUS | C1: SITUAÇÃO | D1: POSIÇÃO | E1: RECOMPRADO | F1: CARTÓRIO
A2: ALUFORCE | B2: A VENCER | C2: A VISTA | D2: LIQUIDADO | E2: A RECEBER | F2: FUNDO
A3: AUGURI | B3: VENCIDO | C3: CARTEIRA | D3: RECOMPRADO | E3: RECEBIDO | F3: ALUFORCE
A4: CAPITAL ANNEX | C4: DISPONÍVEL
A5: CONTINENTAL | C5: OPERADO
A6: DEL MONTE
A7: FAMA
A8: H8
A9: IGNIS
A10: ITAU
A11: LEPTA
A12: ONIX
A13: VALE RIO CLARO

Sheet RESUMO
B1: RESUMO CONTAS A RECEBER
R2: CARTORIO
B3: TOTAL GERAL | E3: =E11+J19+J21+J22+L19+N19 -> #VALUE! | G3: PARCEIRO | H3: A VENCER | I3: VENCIDO | J3: TOTAL | L3: LIQUIDADO | N3: RECOMPRADO | O3: A RECEBER | P3: RECEBIDO | R3: FUNDO | S3: ALUFORCE
B4: CHECK | E4: =FATURAMENTO!H5-RESUMO!E3 -> #VALUE! | G4: AUGURI | H4: =SUMIFS(FATURAMENTO!$H$8:$H$1048576,FATURAMENTO!$M$8:$M$1048576,RESUMO!$H$3,FATURAMENTO!$K$8:$K$1048576,RESUMO!G4) -> 150514.04 | I4: =SUMIFS(FATURAMENTO!$H$8:$H$1048576,FATURAMENTO!$M$8:$M$1048576,$I$3,FATURAMENTO!$K$8:$K$1048576,G4) -> 0 | J4: =H4+I4-N4 -> 150514.04 | L4: =SUMIFS(FATURAMENTO!$H$8:$H$1048576,FATURAMENTO!$M$8:$M$1048576,$L$3,FATURAMENTO!$K$8:$K$1048576,G4) -> 67217.11 | N4: =SUMIFS(FATURAMENTO!$H$8:$H$1048576,FATURAMENTO!$K$8:$K$1048576,RESUMO!$G4,FATURAMENTO!$O$8:$O$1048576,RESUMO!$N$3) -> 0 | O4: =SUMIFS(FATURAMENTO!$H$8:$H$1048576,FATURAMENTO!$K$8:$K$1048576,RESUMO!$G4,FATURAMENTO!$Q$8:$Q$1048576,RESUMO!$O$3) -> 0 | P4: =SUMIFS(FATURAMENTO!$H$8:$H$1048576,FATURAMENTO!$K$8:$K$1048576,RESUMO!$G4,FATURAMENTO!$Q$8:$Q$1048576,$P$3) -> 0 | R4: =SUMIFS(FATURAMENTO!$H$8:$H$1048576,FATURAMENTO!$K$8:$K$1048576,RESUMO!$G4,FATURAMENTO!$S$8:$S$1048576,RESUMO!$R$3) -> 0 | S4: =SUMIFS(FATURAMENTO!$H$8:$H$1048576,FATURAMENTO!$K$8:$K$1048576,RESUMO!$G4,FATURAMENTO!$S$8:$S$1048576,$S$3) -> 0
G5: CAPITAL ANNEX | H5: =SUMIFS(FATURAMENTO!$H$8:$H$1048576,FATURAMENTO!$M$8:$M$1048576,RESUMO!$H$3,FATURAMENTO!$K$8:$K$1048576,RESUMO!G5) -> 414150.34 | I5: =SUMIFS(FATURAMENTO!$H$8:$H$1048576,FATURAMENTO!$M$8:$M$1048576,$I$3,FATURAMENTO!$K$8:$K$1048576,G5) -> 4381.86 | J5: =H5+I5-N5 -> 418532.2 | L5: =SUMIFS(FATURAMENTO!$H$8:$H$1048576,FATURAMENTO!$M$8:$M$1048576,$L$3,FATURAMENTO!$K$8:$K$1048576,G5) -> 247856.98 | N5: =SUMIFS(FATURAMENTO!$H$8:$H$1048576,FATURAMENTO!$K$8:$K$1048576,RESUMO!$G5,FATURAMENTO!$O$8:$O$1048576,RESUMO!$N$3) -> 0 | O5: =SUMIFS(FATURAMENTO!$H$8:$H$1048576,FATURAMENTO!$K$8:$K$1048576,RESUMO!$G5,FATURAMENTO!$Q$8:$Q$1048576,RESUMO!$O$3) -> 0 | P5: =SUMIFS(FATURAMENTO!$H$8:$H$1048576,FATURAMENTO!$K$8:$K$1048576,RESUMO!$G5,FATURAMENTO!$Q$8:$Q$1048576,$P$3) -> 0 | R5: =SUMIFS(FATURAMENTO!$H$8:$H$1048576,FATURAMENTO!$K$8:$K$1048576,RESUMO!$G5,FATURAMENTO!$S$8:$S$1048576,RESUMO!$R$3) -> 0 | S5: =SUMIFS(FATURAMENTO!$H$8:$H$1048576,FATURAMENTO!$K$8:$K$1048576,RESUMO!$G5,FATURAMENTO!$S$8:$S$1048576,$S$3) -> 0
B6: DISPONÍVEL | G6: CONTINENTAL | H6: =SUMIFS(FATURAMENTO!$H$8:$H$1048576,FATURAMENTO!$M$8:$M$1048576,RESUMO!$H$3,FATURAMENTO!$K$8:$K$1048576,RESUMO!G6) -> 0 | I6: =SUMIFS(FATURAMENTO!$H$8:$H$1048576,FATURAMENTO!$M$8:$M$1048576,$I$3,FATURAMENTO!$K$8:$K$1048576,G6) -> 0 | J6: =H6+I6-N6 -> 0 | L6: =SUMIFS(FATURAMENTO!$H$8:$H$1048576,FATURAMENTO!$M$8:$M$1048576,$L$3,FATURAMENTO!$K$8:$K$1048576,G6) -> 0 | N6: =SUMIFS(FATURAMENTO!$H$8:$H$1048576,FATURAMENTO!$K$8:$K$1048576,RESUMO!$G6,FATURAMENTO!$O$8:$O$1048576,RESUMO!$N$3) -> 0 | O6: =SUMIFS(FATURAMENTO!$H$8:$H$1048576,FATURAMENTO!$K$8:$K$1048576,RESUMO!$G6,FATURAMENTO!$Q$8:$Q$1048576,RESUMO!$O$3) -> 0 | P6: =SUMIFS(FATURAMENTO!$H$8:$H$1048576,FATURAMENTO!$K$8:$K$1048576,RESUMO!$G6,FATURAMENTO!$Q$8:$Q$1048576,$P$3) -> 0 | R6: =SUMIFS(FATURAMENTO!$H$8:$H$1048576,FATURAMENTO!$K$8:$K$1048576,RESUMO!$G6,FATURAMENTO!$S$8:$S$1048576,RESUMO!$R$3) -> 0 | S6: =SUMIFS(FATURAMENTO!$H$8:$H$1048576,FATURAMENTO!$K$8:$K$1048576,RESUMO!$G6,FATURAMENTO!$S$8:$S$1048576,$S$3) -> 0
B7: EMPRESA | C7: NF | D7: F9 | E7: TOTAL | G7: DEL MONTE | H7: =SUMIFS(FATURAMENTO!$H$8:$H$1048576,FATURAMENTO!$M$8:$M$1048576,RESUMO!$H$3,FATURAMENTO!$K$8:$K$1048576,RESUMO!G7) -> 4364.1 | I7: =SUMIFS(FATURAMENTO!$H$8:$H$1048576,FATURAMENTO!$M$8:$M$1048576,$I$3,FATURAMENTO!$K$8:$K$1048576,G7) -> 27611 | J7: =H7+I7-N7 -> 31975.1 | L7: =SUMIFS(FATURAMENTO!$H$8:$H$1048576,FATURAMENTO!$M$8:$M$1048576,$L$3,FATURAMENTO!$K$8:$K$1048576,G7) -> 589422.07 | N7: =SUMIFS(FATURAMENTO!$H$8:$H$1048576,FATURAMENTO!$K$8:$K$1048576,RESUMO!$G7,FATURAMENTO!$O$8:$O$1048576,RESUMO!$N$3) -> 0 | O7: =SUMIFS(FATURAMENTO!$H$8:$H$1048576,FATURAMENTO!$K$8:$K$1048576,RESUMO!$G7,FATURAMENTO!$Q$8:$Q$1048576,RESUMO!$O$3) -> 0 | P7: =SUMIFS(FATURAMENTO!$H$8:$H$1048576,FATURAMENTO!$K$8:$K$1048576,RESUMO!$G7,FATURAMENTO!$Q$8:$Q$1048576,$P$3) -> 0 | R7: =SUMIFS(FATURAMENTO!$H$8:$H$1048576,FATURAMENTO!$K$8:$K$1048576,RESUMO!$G7,FATURAMENTO!$S$8:$S$1048576,RESUMO!$R$3) -> 36494 | S7: =SUMIFS(FATURAMENTO!$H$8:$H$1048576,FATURAMENTO!$K$8:$K$1048576,RESUMO!$G7,FATURAMENTO!$S$8:$S$1048576,$S$3) -> 0
B8: ALUFORCE | C8: =SUMIFS(FATURAMENTO!$H:$H,FATURAMENTO!$C:$C,RESUMO!C7,FATURAMENTO!$A:$A,RESUMO!B8,FATURAMENTO!$J:$J,RESUMO!$B$6) -> 0 | D8: =SUMIFS(FATURAMENTO!$H:$H,FATURAMENTO!$C:$C,RESUMO!D7,FATURAMENTO!$A:$A,B8,FATURAMENTO!$J:$J,RESUMO!$B$6) -> 0 | E8: =C8+D8 -> 0 | G8: FAMA | H8: =SUMIFS(FATURAMENTO!$H$8:$H$1048576,FATURAMENTO!$M$8:$M$1048576,RESUMO!$H$3,FATURAMENTO!$K$8:$K$1048576,RESUMO!G8) -> 790342.53 | I8: =SUMIFS(FATURAMENTO!$H$8:$H$1048576,FATURAMENTO!$M$8:$M$1048576,$I$3,FATURAMENTO!$K$8:$K$1048576,G8) -> 0 | J8: =H8+I8-N8 -> 790342.53 | L8: =SUMIFS(FATURAMENTO!$H$8:$H$1048576,FATURAMENTO!$M$8:$M$1048576,$L$3,FATURAMENTO!$K$8:$K$1048576,G8) -> 1387214.4 | N8: =SUMIFS(FATURAMENTO!$H$8:$H$1048576,FATURAMENTO!$K$8:$K$1048576,RESUMO!$G8,FATURAMENTO!$O$8:$O$1048576,RESUMO!$N$3) -> 0 | O8: =SUMIFS(FATURAMENTO!$H$8:$H$1048576,FATURAMENTO!$K$8:$K$1048576,RESUMO!$G8,FATURAMENTO!$Q$8:$Q$1048576,RESUMO!$O$3) -> 0 | P8: =SUMIFS(FATURAMENTO!$H$8:$H$1048576,FATURAMENTO!$K$8:$K$1048576,RESUMO!$G8,FATURAMENTO!$Q$8:$Q$1048576,$P$3) -> 0 | R8: =SUMIFS(FATURAMENTO!$H$8:$H$1048576,FATURAMENTO!$K$8:$K$1048576,RESUMO!$G8,FATURAMENTO!$S$8:$S$1048576,RESUMO!$R$3) -> 38628.76 | S8: =SUMIFS(FATURAMENTO!$H$8:$H$1048576,FATURAMENTO!$K$8:$K$1048576,RESUMO!$G8,FATURAMENTO!$S$8:$S$1048576,$S$3) -> 0
B9: ENERGY | C9: =SUMIFS(FATURAMENTO!$H:$H,FATURAMENTO!$C:$C,RESUMO!C8,FATURAMENTO!$A:$A,RESUMO!B9,FATURAMENTO!$J:$J,RESUMO!$B$6) -> 0 | D9: =SUMIFS(FATURAMENTO!$H:$H,FATURAMENTO!$C:$C,RESUMO!D8,FATURAMENTO!$A:$A,B9,FATURAMENTO!$J:$J,RESUMO!$B$6) -> 0 | E9: =C9+D9 -> 0 | G9: H8 | H9: =SUMIFS(FATURAMENTO!$H$8:$H$1048576,FATURAMENTO!$M$8:$M$1048576,RESUMO!$H$3,FATURAMENTO!$K$8:$K$1048576,RESUMO!G9) -> 404006.17 | I9: =SUMIFS(FATURAMENTO!$H$8:$H$1048576,FATURAMENTO!$M$8:$M$1048576,$I$3,FATURAMENTO!$K$8:$K$1048576,G9) -> 35045.41 | J9: =H9+I9-N9 -> 439051.58 | L9: =SUMIFS(FATURAMENTO!$H$8:$H$1048576,FATURAMENTO!$M$8:$M$1048576,$L$3,FATURAMENTO!$K$8:$K$1048576,G9) -> 380480.24 | N9: =SUMIFS(FATURAMENTO!$H$8:$H$1048576,FATURAMENTO!$K$8:$K$1048576,RESUMO!$G9,FATURAMENTO!$O$8:$O$1048576,RESUMO!$N$3) -> 0 | O9: =SUMIFS(FATURAMENTO!$H$8:$H$1048576,FATURAMENTO!$K$8:$K$1048576,RESUMO!$G9,FATURAMENTO!$Q$8:$Q$1048576,RESUMO!$O$3) -> 0 | P9: =SUMIFS(FATURAMENTO!$H$8:$H$1048576,FATURAMENTO!$K$8:$K$1048576,RESUMO!$G9,FATURAMENTO!$Q$8:$Q$1048576,$P$3) -> 0 | R9: =SUMIFS(FATURAMENTO!$H$8:$H$1048576,FATURAMENTO!$K$8:$K$1048576,RESUMO!$G9,FATURAMENTO!$S$8:$S$1048576,RESUMO!$R$3) -> 17192 | S9: =SUMIFS(FATURAMENTO!$H$8:$H$1048576,FATURAMENTO!$K$8:$K$1048576,RESUMO!$G9,FATURAMENTO!$S$8:$S$1048576,$S$3) -> 0
B10: LABOR | C10: =SUMIFS(FATURAMENTO!$H:$H,FATURAMENTO!$C:$C,RESUMO!C9,FATURAMENTO!$A:$A,RESUMO!B10,FATURAMENTO!$J:$J,RESUMO!$B$6) -> 0 | D10: =SUMIFS(FATURAMENTO!$H:$H,FATURAMENTO!$C:$C,RESUMO!D9,FATURAMENTO!$A:$A,B10,FATURAMENTO!$J:$J,RESUMO!$B$6) -> 0 | E10: =C10+D10 -> 0 | G10: KHAVA | H10: =SUMIFS(FATURAMENTO!$H$8:$H$1048576,FATURAMENTO!$M$8:$M$1048576,RESUMO!$H$3,FATURAMENTO!$K$8:$K$1048576,RESUMO!G10) -> 0 | I10: =SUMIFS(FATURAMENTO!$H$8:$H$1048576,FATURAMENTO!$M$8:$M$1048576,$I$3,FATURAMENTO!$K$8:$K$1048576,G10) -> 0 | J10: =H10+I10-N10 -> 0 | L10: =SUMIFS(FATURAMENTO!$H$8:$H$1048576,FATURAMENTO!$M$8:$M$1048576,$L$3,FATURAMENTO!$K$8:$K$1048576,G10) -> 0 | N10: =SUMIFS(FATURAMENTO!$H$8:$H$1048576,FATURAMENTO!$K$8:$K$1048576,RESUMO!$G10,FATURAMENTO!$O$8:$O$1048576,RESUMO!$N$3) -> 0 | O10: =SUMIFS(FATURAMENTO!$H$8:$H$1048576,FATURAMENTO!$K$8:$K$1048576,RESUMO!$G10,FATURAMENTO!$Q$8:$Q$1048576,RESUMO!$O$3) -> 0 | P10: =SUMIFS(FATURAMENTO!$H$8:$H$1048576,FATURAMENTO!$K$8:$K$1048576,RESUMO!$G10,FATURAMENTO!$Q$8:$Q$1048576,$P$3) -> 0 | R10: =SUMIFS(FATURAMENTO!$H$8:$H$1048576,FATURAMENTO!$K$8:$K$1048576,RESUMO!$G10,FATURAMENTO!$S$8:$S$1048576,RESUMO!$R$3) -> 0 | S10: =SUMIFS(FATURAMENTO!$H$8:$H$1048576,FATURAMENTO!$K$8:$K$1048576,RESUMO!$G10,FATURAMENTO!$S$8:$S$1048576,$S$3) -> 0
C11: =SUM(C8:C10) -> 0 | D11: =SUM(D8:D10) -> 0 | E11: =C11+D11 -> 0 | G11: LEPTA | H11: =SUMIFS(FATURAMENTO!$H$8:$H$1048576,FATURAMENTO!$M$8:$M$1048576,RESUMO!$H$3,FATURAMENTO!$K$8:$K$1048576,RESUMO!G11) -> 125131.28 | I11: =SUMIFS(FATURAMENTO!$H$8:$H$1048576,FATURAMENTO!$M$8:$M$1048576,$I$3,FATURAMENTO!$K$8:$K$1048576,G11) -> 0 | J11: =H11+I11-N11 -> 125131.28 | L11: =SUMIFS(FATURAMENTO!$H$8:$H$1048576,FATURAMENTO!$M$8:$M$1048576,$L$3,FATURAMENTO!$K$8:$K$1048576,G11) -> 345775 | N11: =SUMIFS(FATURAMENTO!$H$8:$H$1048576,FATURAMENTO!$K$8:$K$1048576,RESUMO!$G11,FATURAMENTO!$O$8:$O$1048576,RESUMO!$N$3) -> 0 | O11: =SUMIFS(FATURAMENTO!$H$8:$H$1048576,FATURAMENTO!$K$8:$K$1048576,RESUMO!$G11,FATURAMENTO!$Q$8:$Q$1048576,RESUMO!$O$3) -> 0 | P11: =SUMIFS(FATURAMENTO!$H$8:$H$1048576,FATURAMENTO!$K$8:$K$1048576,RESUMO!$G11,FATURAMENTO!$Q$8:$Q$1048576,$P$3) -> 0 | R11: =SUMIFS(FATURAMENTO!$H$8:$H$1048576,FATURAMENTO!$K$8:$K$1048576,RESUMO!$G11,FATURAMENTO!$S$8:$S$1048576,RESUMO!$R$3) -> 0 | S11: =SUMIFS(FATURAMENTO!$H$8:$H$1048576,FATURAMENTO!$K$8:$K$1048576,RESUMO!$G11,FATURAMENTO!$S$8:$S$1048576,$S$3) -> 0
G12: ONIX | H12: =SUMIFS(FATURAMENTO!$H$8:$H$1048576,FATURAMENTO!$M$8:$M$1048576,RESUMO!$H$3,FATURAMENTO!$K$8:$K$1048576,RESUMO!G12) -> 248763.27 | I12: =SUMIFS(FATURAMENTO!$H$8:$H$1048576,FATURAMENTO!$M$8:$M$1048576,$I$3,FATURAMENTO!$K$8:$K$1048576,G12) -> 0 | J12: =H12+I12-N12 -> 248763.27 | L12: =SUMIFS(FATURAMENTO!$H$8:$H$1048576,FATURAMENTO!$M$8:$M$1048576,$L$3,FATURAMENTO!$K$8:$K$1048576,G12) -> 26137.19 | N12: =SUMIFS(FATURAMENTO!$H$8:$H$1048576,FATURAMENTO!$K$8:$K$1048576,RESUMO!$G12,FATURAMENTO!$O$8:$O$1048576,RESUMO!$N$3) -> 0 | O12: =SUMIFS(FATURAMENTO!$H$8:$H$1048576,FATURAMENTO!$K$8:$K$1048576,RESUMO!$G12,FATURAMENTO!$Q$8:$Q$1048576,RESUMO!$O$3) -> 0 | P12: =SUMIFS(FATURAMENTO!$H$8:$H$1048576,FATURAMENTO!$K$8:$K$1048576,RESUMO!$G12,FATURAMENTO!$Q$8:$Q$1048576,$P$3) -> 0 | R12: =SUMIFS(FATURAMENTO!$H$8:$H$1048576,FATURAMENTO!$K$8:$K$1048576,RESUMO!$G12,FATURAMENTO!$S$8:$S$1048576,RESUMO!$R$3) -> 0 | S12: =SUMIFS(FATURAMENTO!$H$8:$H$1048576,FATURAMENTO!$K$8:$K$1048576,RESUMO!$G12,FATURAMENTO!$S$8:$S$1048576,$S$3) -> 0
G13: VALE RIO CLARO | H13: =SUMIFS(FATURAMENTO!$H$8:$H$1048576,FATURAMENTO!$M$8:$M$1048576,RESUMO!$H$3,FATURAMENTO!$K$8:$K$1048576,RESUMO!G13) -> 33557.59 | I13: =SUMIFS(FATURAMENTO!$H$8:$H$1048576,FATURAMENTO!$M$8:$M$1048576,$I$3,FATURAMENTO!$K$8:$K$1048576,G13) -> 22669.17 | J13: =H13+I13-N13 -> 38412.18 | L13: =SUMIFS(FATURAMENTO!$H$8:$H$1048576,FATURAMENTO!$M$8:$M$1048576,$L$3,FATURAMENTO!$K$8:$K$1048576,G13) -> 361255.92 | N13: =SUMIFS(FATURAMENTO!$H$8:$H$1048576,FATURAMENTO!$K$8:$K$1048576,RESUMO!$G13,FATURAMENTO!$O$8:$O$1048576,RESUMO!$N$3) -> 17814.58 | O13: =SUMIFS(FATURAMENTO!$H$8:$H$1048576,FATURAMENTO!$K$8:$K$1048576,RESUMO!$G13,FATURAMENTO!$Q$8:$Q$1048576,RESUMO!$O$3) -> 1333.33 | P13: =SUMIFS(FATURAMENTO!$H$8:$H$1048576,FATURAMENTO!$K$8:$K$1048576,RESUMO!$G13,FATURAMENTO!$Q$8:$Q$1048576,$P$3) -> 4540 | R13: =SUMIFS(FATURAMENTO!$H$8:$H$1048576,FATURAMENTO!$K$8:$K$1048576,RESUMO!$G13,FATURAMENTO!$S$8:$S$1048576,RESUMO!$R$3) -> 0 | S13: =SUMIFS(FATURAMENTO!$H$8:$H$1048576,FATURAMENTO!$K$8:$K$1048576,RESUMO!$G13,FATURAMENTO!$S$8:$S$1048576,$S$3) -> 1333.33
J14: =H14+I14 -> 0 | L14: =SUMIFS(FATURAMENTO!$H$8:$H$1048576,FATURAMENTO!$M$8:$M$1048576,$L$3,FATURAMENTO!$K$8:$K$1048576,G14) -> 0 | N14: =SUMIFS(FATURAMENTO!$H$8:$H$1048576,FATURAMENTO!$Q$8:$Q$1048576,RESUMO!$N$3,FATURAMENTO!$K$8:$K$1048576,RESUMO!$G14) -> 0
J17: =H17+I17 -> 0 | L17: =SUMIFS(FATURAMENTO!$H$8:$H$1048576,FATURAMENTO!$M$8:$M$1048576,$L$3,FATURAMENTO!$K$8:$K$1048576,G17) -> 0 | N17: =SUMIFS(FATURAMENTO!$H$8:$H$1048576,FATURAMENTO!$Q$8:$Q$1048576,RESUMO!$N$3,FATURAMENTO!$K$8:$K$1048576,RESUMO!$G17) -> 0
J18: =H18+I18 -> 0 | L18: =SUMIFS(FATURAMENTO!$H$8:$H$1048576,FATURAMENTO!$M$8:$M$1048576,$L$3,FATURAMENTO!$K$8:$K$1048576,G18) -> 0 | N18: =SUMIFS(FATURAMENTO!$H$8:$H$1048576,FATURAMENTO!$Q$8:$Q$1048576,RESUMO!$N$3,FATURAMENTO!$K$8:$K$1048576,RESUMO!$G18) -> 0
H19: =SUM(H4:H13) -> 2170829.3 | I19: =SUM(I4:I13) -> 89707.44 | J19: =SUM(J4:J13) -> 2242722.2 | L19: =SUM(L4:L13) -> 3405359 | N19: =SUM(N4:N18) -> 17814.58 | O19: =SUM(O4:O18) -> 1333.33 | P19: =SUM(P4:P18) -> 4540 | R19: =SUM(R4:R18) -> 92314.76 | S19: =SUM(S4:S18) -> 1333.33
G21: A VISTA | H21: =SUMIFS(FATURAMENTO!$H$20:$H$1048576,FATURAMENTO!$M$20:$M$1048576,RESUMO!$H$3,FATURAMENTO!$J$747:$J$1048576,RESUMO!G21) -> #VALUE! | I21: =SUMIFS(FATURAMENTO!$H$20:$H$1048576,FATURAMENTO!$M$20:$M$1048576,$I$3,FATURAMENTO!$J$747:$J$1048576,G21) -> #VALUE! | J21: =H21+I21 -> #VALUE! | L21: =SUMIFS(FATURAMENTO!$H$8:$H$1048576,FATURAMENTO!$M$8:$M$1048576,$L$3,FATURAMENTO!$K$8:$K$1048576,G21) -> 0
G22: CARTEIRA | H22: =SUMIFS(FATURAMENTO!$H$20:$H$1048576,FATURAMENTO!$M$20:$M$1048576,RESUMO!$H$3,FATURAMENTO!$J$747:$J$1048576,RESUMO!G22) -> #VALUE! | I22: =SUMIFS(FATURAMENTO!$H$20:$H$1048576,FATURAMENTO!$M$20:$M$1048576,$I$3,FATURAMENTO!$J$747:$J$1048576,G22) -> #VALUE! | J22: =H22+I22 -> #VALUE! | L22: =SUMIFS(FATURAMENTO!$H$8:$H$1048576,FATURAMENTO!$M$8:$M$1048576,$L$3,FATURAMENTO!$K$8:$K$1048576,G22) -> 0

Sheet FATURAMENTO
G5: TOTAL | H5: =SUM(H8:H1048576) -> 6418105.4 | I5: =TODAY() -> 46098
A6: DADOS DA NF | G6: SUBTOTAL | H6: =SUBTOTAL(9,H8:H1048576) -> 6418105.4 | I6: HOJE | K6: OPERAÇÕES FINANCEIRAS | N6: VENCIDO | O6: LIQUIDADO/RECOMPRADO | Q6: STATUS DA RECOMPRA
A7: EMPRESA | B7: EMISSÃO | C7: TIPO | D7: NFe | E7: P | F7: CLIENTE | G7: CNPJ | H7: VALOR P | I7: VCTO | J7: SITUAÇÃO | K7: PORTADOR | L7: DATA | M7: STATUS | N7: DIAS | O7: POSIÇÃO | P7: DATA2 | Q7: RECOMPRADO | R7: DATA3 | S7: CARTORIO | T7: OBSERVAÇÃO | U7: ACEITA TROCA FACTORY | V7: COMISSÁRIA
A8: ALUFORCE | B8: 45966 | C8: NF | D8: 165 | E8: 003/003 | F8: R.N.A METAIS E DISTRIBUIDORA LTDA | G8: 06.269.699/0001-76 | H8: 15586.66 | I8: 46031 | J8: OPERADO | K8: DEL MONTE | L8: 46003 | M8: =IF(Tabela4[[#This Row],[RECOMPRADO]]="RECEBIDO","LIQUIDADO",IF(O8="LIQUIDADO","LIQUIDADO",IF(I8<$I$5,"VENCIDO","A VENCER"))) -> LIQUIDADO | N8: =IF(Tabela4[[#This Row],[STATUS]]="LIQUIDADO","",Tabela4[[#This Row],[VCTO]]-$I$5) | O8: LIQUIDADO
A9: ENERGY | B9: 45971 | C9: NF | D9: 645 | E9: 002/003 | F9: 0003Z475 | G9: 20.590.831/0001-78 | H9: 1666.66 | I9: 46016 | J9: OPERADO | K9: BANCO | M9: =IF(Tabela4[[#This Row],[RECOMPRADO]]="RECEBIDO","LIQUIDADO",IF(O9="LIQUIDADO","LIQUIDADO",IF(I9<$I$5,"VENCIDO","A VENCER"))) -> LIQUIDADO | N9: =IF(Tabela4[[#This Row],[STATUS]]="LIQUIDADO","",Tabela4[[#This Row],[VCTO]]-$I$5) | O9: LIQUIDADO
A10: ENERGY | B10: 45971 | C10: F9 | D10: 645 | E10: 003/003 | F10: BELA CAAPORA EMPREENDIMENTOS IMOBILIARIOS SPE LTDA | G10: 20.590.831/0001-78 | H10: 1666.68 | I10: 46031 | J10: OPERADO | K10: H8 | L10: 46025 | M10: =IF(Tabela4[[#This Row],[RECOMPRADO]]="RECEBIDO","LIQUIDADO",IF(O10="LIQUIDADO","LIQUIDADO",IF(I10<$I$5,"VENCIDO","A VENCER"))) -> LIQUIDADO | N10: =IF(Tabela4[[#This Row],[STATUS]]="LIQUIDADO","",Tabela4[[#This Row],[VCTO]]-$I$5) | O10: LIQUIDADO
A11: ENERGY | B11: 45971 | C11: NF | D11: 645 | E11: 001/003 | F11: BELA CAAPORA EMPREENDIMENTOS IMOBILIARIOS SPE LTDA | G11: 20.590.831/0001-78 | H11: 3513.33 | I11: 46001 | J11: OPERADO | K11: BANCO | M11: =IF(Tabela4[[#This Row],[RECOMPRADO]]="RECEBIDO","LIQUIDADO",IF(O11="LIQUIDADO","LIQUIDADO",IF(I11<$I$5,"VENCIDO","A VENCER"))) -> LIQUIDADO | N11: =IF(Tabela4[[#This Row],[STATUS]]="LIQUIDADO","",Tabela4[[#This Row],[VCTO]]-$I$5) | O11: LIQUIDADO
A12: ENERGY | B12: 45971 | C12: NF | D12: 645 | E12: 003/003 | F12: BELA CAAPORA EMPREENDIMENTOS IMOBILIARIOS SPE LTDA | G12: 20.590.831/0001-78 | H12: 3446.66 | I12: 46031 | J12: OPERADO | K12: BANCO | M12: =IF(Tabela4[[#This Row],[RECOMPRADO]]="RECEBIDO","LIQUIDADO",IF(O12="LIQUIDADO","LIQUIDADO",IF(I12<$I$5,"VENCIDO","A VENCER"))) -> LIQUIDADO | N12: =IF(Tabela4[[#This Row],[STATUS]]="LIQUIDADO","",Tabela4[[#This Row],[VCTO]]-$I$5) | O12: LIQUIDADO
A13: ENERGY | B13: 45973 | C13: NF | D13: 653 | E13: 006/006 | F13: PONTO CERTO MATERIAIS ELETRIVOS E HIDRAULICOS LTDA | G13: 10.821.336/0001-79 | H13: 3035.85 | I13: 46030 | J13: OPERADO | K13: FAMA | L13: 46003 | M13: =IF(Tabela4[[#This Row],[RECOMPRADO]]="RECEBIDO","LIQUIDADO",IF(O13="LIQUIDADO","LIQUIDADO",IF(I13<$I$5,"VENCIDO","A VENCER"))) -> LIQUIDADO | N13: =IF(Tabela4[[#This Row],[STATUS]]="LIQUIDADO","",Tabela4[[#This Row],[VCTO]]-$I$5) | O13: LIQUIDADO
A14: ENERGY | B14: 45973 | C14: NF | D14: 652 | E14: 006/006 | F14: GLACAI INDUSTRIA DE SORVETES LTDA | G14: 30.062.482/0061-06 | H14: 2400 | I14: 46030 | J14: OPERADO | K14: FAMA | L14: 46003 | M14: =IF(Tabela4[[#This Row],[RECOMPRADO]]="RECEBIDO","LIQUIDADO",IF(O14="LIQUIDADO","LIQUIDADO",IF(I14<$I$5,"VENCIDO","A VENCER"))) -> LIQUIDADO | N14: =IF(Tabela4[[#This Row],[STATUS]]="LIQUIDADO","",Tabela4[[#This Row],[VCTO]]-$I$5) | O14: LIQUIDADO
A15: ENERGY | B15: 45975 | C15: NF | D15: 658 | E15: 005/005 | F15: ELETRICA BEL MATERIAIS ELETRICOS LTDA | G15: 58.246.059/0001-44 | H15: 2600.6 | I15: 46031 | J15: OPERADO | K15: VALE RIO CLARO | L15: 46027 | M15: =IF(Tabela4[[#This Row],[RECOMPRADO]]="RECEBIDO","LIQUIDADO",IF(O15="LIQUIDADO","LIQUIDADO",IF(I15<$I$5,"VENCIDO","A VENCER"))) -> LIQUIDADO | N15: =IF(Tabela4[[#This Row],[STATUS]]="LIQUIDADO","",Tabela4[[#This Row],[VCTO]]-$I$5) | O15: LIQUIDADO
A16: ALUFORCE | B16: 45978 | C16: NF | D16: 188 | E16: 003/003 | F16: EGIDIO & CAETANO - EXECUCOES ELETRICAS LTDA | G16: 23.899.714/0001-89 | H16: 10432.61 | I16: 46069 | J16: OPERADO | K16: FAMA | L16: 46003 | M16: =IF(Tabela4[[#This Row],[RECOMPRADO]]="RECEBIDO","LIQUIDADO",IF(O16="LIQUIDADO","LIQUIDADO",IF(I16<$I$5,"VENCIDO","A VENCER"))) -> LIQUIDADO | N16: =IF(Tabela4[[#This Row],[STATUS]]="LIQUIDADO","",Tabela4[[#This Row],[VCTO]]-$I$5) | O16: LIQUIDADO
A17: LABOR | B17: 45978 | C17: NF | D17: 4255 | E17: 006/006 | F17: J G COMERCIO DE MATERIAL ELETRICO LTDA | G17: 14.638.183/0001-80 | H17: 3225 | I17: 46044 | J17: OPERADO | K17: FAMA | L17: 46003 | M17: =IF(Tabela4[[#This Row],[RECOMPRADO]]="RECEBIDO","LIQUIDADO",IF(O17="LIQUIDADO","LIQUIDADO",IF(I17<$I$5,"VENCIDO","A VENCER"))) -> LIQUIDADO | N17: =IF(Tabela4[[#This Row],[STATUS]]="LIQUIDADO","",Tabela4[[#This Row],[VCTO]]-$I$5) | O17: LIQUIDADO
A18: LABOR | B18: 45978 | C18: NF | D18: 4259 | E18: 001/001 | F18: EXCEL DISTRIBUICAO DE MATERIAL ELETRICO LTDA | G18: 07.931.533/0001-36 | H18: 38628.76 | I18: 46066 | J18: OPERADO | K18: FAMA | L18: 46003 | M18: =IF(Tabela4[[#This Row],[RECOMPRADO]]="RECEBIDO","LIQUIDADO",IF(O18="LIQUIDADO","LIQUIDADO",IF(I18<$I$5,"VENCIDO","A VENCER"))) -> LIQUIDADO | N18: =IF(Tabela4[[#This Row],[STATUS]]="LIQUIDADO","",Tabela4[[#This Row],[VCTO]]-$I$5) | O18: LIQUIDADO | S18: FUNDO | T18: cliente informa que efetuou o pagamento no cartório porem consta como vencido no relatório
A19: ALUFORCE | B19: 45978 | C19: NF | D19: 191 | E19: 004/005 | F19: ANGELA A J BUSATTO & CIA LTDA | G19: 09.356.946/0001-60 | H19: 1854 | I19: 46031 | J19: OPERADO | K19: FAMA | L19: 46003 | M19: =IF(Tabela4[[#This Row],[RECOMPRADO]]="RECEBIDO","LIQUIDADO",IF(O19="LIQUIDADO","LIQUIDADO",IF(I19<$I$5,"VENCIDO","A VENCER"))) -> LIQUIDADO | N19: =IF(Tabela4[[#This Row],[STATUS]]="LIQUIDADO","",Tabela4[[#This Row],[VCTO]]-$I$5) | O19: LIQUIDADO
A20: LABOR | B20: 45978 | C20: NF | D20: 4255 | E20: 005/006 | F20: J G COMERCIO DE MATERIAL ELETRICO LTDA | G20: 14.638.183/0001-80 | H20: 3225 | I20: 46037 | J20: OPERADO | K20: FAMA | L20: 46003 | M20: =IF(Tabela4[[#This Row],[RECOMPRADO]]="RECEBIDO","LIQUIDADO",IF(O20="LIQUIDADO","LIQUIDADO",IF(I20<$I$5,"VENCIDO","A VENCER"))) -> LIQUIDADO | N20: =IF(Tabela4[[#This Row],[STATUS]]="LIQUIDADO","",Tabela4[[#This Row],[VCTO]]-$I$5) | O20: LIQUIDADO
A21: LABOR | B21: 45978 | C21: NF | D21: 4255 | E21: 004/006 | F21: J G COMERCIO DE MATERIAL ELETRICO LTDA | G21: 14.638.183/0001-80 | H21: 3225 | I21: 46030 | J21: OPERADO | K21: FAMA | L21: 46003 | M21: =IF(Tabela4[[#This Row],[RECOMPRADO]]="RECEBIDO","LIQUIDADO",IF(O21="LIQUIDADO","LIQUIDADO",IF(I21<$I$5,"VENCIDO","A VENCER"))) -> LIQUIDADO | N21: =IF(Tabela4[[#This Row],[STATUS]]="LIQUIDADO","",Tabela4[[#This Row],[VCTO]]-$I$5) | O21: LIQUIDADO
A22: LABOR | B22: 45978 | C22: NF | D22: 4256 | E22: 004/004 | F22: TOZZI MATERIAIS ELETRICOS LTDA | G22: 40.202.099/0001-29 | H22: 2242.5 | I22: 46031 | J22: OPERADO | K22: FAMA | L22: 46003 | M22: =IF(Tabela4[[#This Row],[RECOMPRADO]]="RECEBIDO","LIQUIDADO",IF(O22="LIQUIDADO","LIQUIDADO",IF(I22<$I$5,"VENCIDO","A VENCER"))) -> LIQUIDADO | N22: =IF(Tabela4[[#This Row],[STATUS]]="LIQUIDADO","",Tabela4[[#This Row],[VCTO]]-$I$5) | O22: LIQUIDADO
A23: LABOR | B23: 45978 | C23: NF | D23: 4258 | E23: 004/004 | F23: D F TOFFOLI MATERIAL ELETRICO LTDA | G23: 28.164.842/0001-06 | H23: 1751.25 | I23: 46031 | J23: OPERADO | K23: FAMA | L23: 46003 | M23: =IF(Tabela4[[#This Row],[RECOMPRADO]]="RECEBIDO","LIQUIDADO",IF(O23="LIQUIDADO","LIQUIDADO",IF(I23<$I$5,"VENCIDO","A VENCER"))) -> LIQUIDADO | N23: =IF(Tabela4[[#This Row],[STATUS]]="LIQUIDADO","",Tabela4[[#This Row],[VCTO]]-$I$5) | O23: LIQUIDADO
A24: LABOR | B24: 45978 | C24: NF | D24: 4253 | E24: 005/005 | F24: RDM CAMPINAS COMERCIO DE MATERIAIS ELETRICOS LTDA | G24: 40.919.972/0001-07 | H24: 1880 | I24: 46034 | J24: OPERADO | K24: FAMA | L24: 46003 | M24: =IF(Tabela4[[#This Row],[RECOMPRADO]]="RECEBIDO","LIQUIDADO",IF(O24="LIQUIDADO","LIQUIDADO",IF(I24<$I$5,"VENCIDO","A VENCER"))) -> LIQUIDADO | N24: =IF(Tabela4[[#This Row],[STATUS]]="LIQUIDADO","",Tabela4[[#This Row],[VCTO]]-$I$5) | O24: LIQUIDADO
A25: LABOR | B25: 45978 | C25: NF | D25: 4251 | E25: 005/005 | F25: SUPER FIO LTDA | G25: 57.231.501/0001-04 | H25: 1064 | I25: 46034 | J25: OPERADO | K25: FAMA | L25: 46003 | M25: =IF(Tabela4[[#This Row],[RECOMPRADO]]="RECEBIDO","LIQUIDADO",IF(O25="LIQUIDADO","LIQUIDADO",IF(I25<$I$5,"VENCIDO","A VENCER"))) -> LIQUIDADO | N25: =IF(Tabela4[[#This Row],[STATUS]]="LIQUIDADO","",Tabela4[[#This Row],[VCTO]]-$I$5) | O25: LIQUIDADO
A26: ALUFORCE | B26: 45978 | C26: NF | D26: 188 | E26: 002/003 | F26: EGIDIO & CAETANO - EXECUCOES ELETRICAS LTDA | G26: 23.899.714/0001-89 | H26: 10432.62 | I26: 46039 | J26: OPERADO | K26: FAMA | L26: 46003 | M26: =IF(Tabela4[[#This Row],[RECOMPRADO]]="RECEBIDO","LIQUIDADO",IF(O26="LIQUIDADO","LIQUIDADO",IF(I26<$I$5,"VENCIDO","A VENCER"))) -> LIQUIDADO | N26: =IF(Tabela4[[#This Row],[STATUS]]="LIQUIDADO","",Tabela4[[#This Row],[VCTO]]-$I$5) | O26: LIQUIDADO
A27: ALUFORCE | B27: 45978 | C27: NF | D27: 191 | E27: 005/005 | F27: ANGELA A J BUSATTO & CIA LTDA | G27: 09.356.946/0001-60 | H27: 1854 | I27: 46038 | J27: OPERADO | K27: FAMA | L27: 46003 | M27: =IF(Tabela4[[#This Row],[RECOMPRADO]]="RECEBIDO","LIQUIDADO",IF(O27="LIQUIDADO","LIQUIDADO",IF(I27<$I$5,"VENCIDO","A VENCER"))) -> LIQUIDADO | N27: =IF(Tabela4[[#This Row],[STATUS]]="LIQUIDADO","",Tabela4[[#This Row],[VCTO]]-$I$5) | O27: LIQUIDADO
A28: ALUFORCE | B28: 45980 | C28: NF | D28: 194 | E28: 002/003 | F28: COMERCIAL MARTINS LTDA | G28: 20.891.953/0001-02 | H28: 2006.75 | I28: 46042 | J28: OPERADO | K28: H8 | L28: 46025 | M28: =IF(Tabela4[[#This Row],[RECOMPRADO]]="RECEBIDO","LIQUIDADO",IF(O28="LIQUIDADO","LIQUIDADO",IF(I28<$I$5,"VENCIDO","A VENCER"))) -> LIQUIDADO | N28: =IF(Tabela4[[#This Row],[STATUS]]="LIQUIDADO","",Tabela4[[#This Row],[VCTO]]-$I$5) | O28: LIQUIDADO
A29: ALUFORCE | B29: 45980 | C29: NF | D29: 194 | E29: 003/003 | F29: COMERCIAL MARTINS LTDA | G29: 20.891.953/0001-02 | H29: 2006.75 | I29: 46072 | J29: OPERADO | K29: H8 | L29: 46025 | M29: =IF(Tabela4[[#This Row],[RECOMPRADO]]="RECEBIDO","LIQUIDADO",IF(O29="LIQUIDADO","LIQUIDADO",IF(I29<$I$5,"VENCIDO","A VENCER"))) -> LIQUIDADO | N29: =IF(Tabela4[[#This Row],[STATUS]]="LIQUIDADO","",Tabela4[[#This Row],[VCTO]]-$I$5) | O29: LIQUIDADO
A30: ALUFORCE | B30: 45980 | C30: F9 | D30: 194 | E30: 002/003 | F30: COMERCIAL MARTINS LTDA | G30: 20.891.953/0001-02 | H30: 2006.75 | I30: 46042 | J30: OPERADO | K30: H8 | L30: 46025 | M30: =IF(Tabela4[[#This Row],[RECOMPRADO]]="RECEBIDO","LIQUIDADO",IF(O30="LIQUIDADO","LIQUIDADO",IF(I30<$I$5,"VENCIDO","A VENCER"))) -> LIQUIDADO | N30: =IF(Tabela4[[#This Row],[STATUS]]="LIQUIDADO","",Tabela4[[#This Row],[VCTO]]-$I$5) | O30: LIQUIDADO
A31: ALUFORCE | B31: 45980 | C31: F9 | D31: 194 | E31: 003/003 | F31: COMERCIAL MARTINS LTDA | G31: 20.891.953/0001-02 | H31: 2006.75 | I31: 46072 | J31: OPERADO | K31: H8 | L31: 46025 | M31: =IF(Tabela4[[#This Row],[RECOMPRADO]]="RECEBIDO","LIQUIDADO",IF(O31="LIQUIDADO","LIQUIDADO",IF(I31<$I$5,"VENCIDO","A VENCER"))) -> LIQUIDADO | N31: =IF(Tabela4[[#This Row],[STATUS]]="LIQUIDADO","",Tabela4[[#This Row],[VCTO]]-$I$5) | O31: LIQUIDADO
A32: LABOR | B32: 45980 | C32: NF | D32: 4261 | E32: 003/003 | F32: CORREIA ATACADO MATERIAL ELETRICO LTDA | G32: 07.453.496/0001-06 | H32: 3444 | I32: 46042 | J32: OPERADO | K32: FAMA | L32: 46003 | M32: =IF(Tabela4[[#This Row],[RECOMPRADO]]="RECEBIDO","LIQUIDADO",IF(O32="LIQUIDADO","LIQUIDADO",IF(I32<$I$5,"VENCIDO","A VENCER"))) -> LIQUIDADO | N32: =IF(Tabela4[[#This Row],[STATUS]]="LIQUIDADO","",Tabela4[[#This Row],[VCTO]]-$I$5) | O32: LIQUIDADO
A33: LABOR | B33: 45980 | C33: NF | D33: 4262 | E33: 001/001 | F33: EXCEL DISTRIBUICAO DE MATERIAL ELETRICO LTDA | G33: 07.931.533/0001-36 | H33: 4151.6 | I33: 46066 | J33: OPERADO | K33: FAMA | L33: 46003 | M33: =IF(Tabela4[[#This Row],[RECOMPRADO]]="RECEBIDO","LIQUIDADO",IF(O33="LIQUIDADO","LIQUIDADO",IF(I33<$I$5,"VENCIDO","A VENCER"))) -> LIQUIDADO | N33: =IF(Tabela4[[#This Row],[STATUS]]="LIQUIDADO","",Tabela4[[#This Row],[VCTO]]-$I$5) | O33: LIQUIDADO | T33: prorrogada
A34: LABOR | B34: 45980 | C34: NF | D34: 4260 | E34: 001 | F34: JULIO CESAR F SOUSA SERVICOS LTDA | G34: 46.864.361/0001-87 | H34: 5875 | I34: 46012 | J34: CARTEIRA | K34: ALUFORCE | L34: 46052 | M34: =IF(Tabela4[[#This Row],[RECOMPRADO]]="RECEBIDO","LIQUIDADO",IF(O34="LIQUIDADO","LIQUIDADO",IF(I34<$I$5,"VENCIDO","A VENCER"))) -> VENCIDO | N34: =IF(Tabela4[[#This Row],[STATUS]]="LIQUIDADO","",Tabela4[[#This Row],[VCTO]]-$I$5) -> -86 | O34: RECOMPRADO | P34: 46052 | S34: FUNDO | T34: juridico
A35: LABOR | B35: 45980 | C35: NF | D35: 4260 | E35: 002 | F35: JULIO CESAR F SOUSA SERVICOS LTDA | G35: 46.864.361/0001-87 | H35: 5875 | I35: 46027 | J35: CARTEIRA | K35: ALUFORCE | L35: 46052 | M35: =IF(Tabela4[[#This Row],[RECOMPRADO]]="RECEBIDO","LIQUIDADO",IF(O35="LIQUIDADO","LIQUIDADO",IF(I35<$I$5,"VENCIDO","A VENCER"))) -> VENCIDO | N35: =IF(Tabela4[[#This Row],[STATUS]]="LIQUIDADO","",Tabela4[[#This Row],[VCTO]]-$I$5) -> -71 | O35: RECOMPRADO | P35: 46052 | S35: FUNDO | T35: juridico
A36: LABOR | B36: 45980 | C36: NF | D36: 4260 | E36: 003 | F36: JULIO CESAR F SOUSA SERVICOS LTDA | G36: 46.864.361/0001-87 | H36: 5875 | I36: 46042 | J36: CARTEIRA | K36: ALUFORCE | L36: 46052 | M36: =IF(Tabela4[[#This Row],[RECOMPRADO]]="RECEBIDO","LIQUIDADO",IF(O36="LIQUIDADO","LIQUIDADO",IF(I36<$I$5,"VENCIDO","A VENCER"))) -> VENCIDO | N36: =IF(Tabela4[[#This Row],[STATUS]]="LIQUIDADO","",Tabela4[[#This Row],[VCTO]]-$I$5) -> -56 | O36: RECOMPRADO | P36: 46052 | S36: FUNDO | T36: juridico
A37: LABOR | B37: 45985 | C37: NF | D37: 4264 | E37: 005/005 | F37: PETROLLUZ MATERIAIS ELETRICOS LTDA | G37: 02.493.174/0001-69 | H37: 2028 | I37: 46043 | J37: OPERADO | K37: H8 | L37: 46025 | M37: =IF(Tabela4[[#This Row],[RECOMPRADO]]="RECEBIDO","LIQUIDADO",IF(O37="LIQUIDADO","LIQUIDADO",IF(I37<$I$5,"VENCIDO","A VENCER"))) -> LIQUIDADO | N37: =IF(Tabela4[[#This Row],[STATUS]]="LIQUIDADO","",Tabela4[[#This Row],[VCTO]]-$I$5) | O37: LIQUIDADO
A38: LABOR | B38: 45985 | C38: NF | D38: 4264 | E38: 003/005 | F38: PETROLLUZ MATERIAIS ELETRICOS LTDA | G38: 02.493.174/0001-69 | H38: 2028 | I38: 46029 | J38: OPERADO | K38: H8 | L38: 46025 | M38: =IF(Tabela4[[#This Row],[RECOMPRADO]]="RECEBIDO","LIQUIDADO",IF(O38="LIQUIDADO","LIQUIDADO",IF(I38<$I$5,"VENCIDO","A VENCER"))) -> LIQUIDADO | N38: =IF(Tabela4[[#This Row],[STATUS]]="LIQUIDADO","",Tabela4[[#This Row],[VCTO]]-$I$5) | O38: LIQUIDADO
A39: LABOR | B39: 45985 | C39: NF | D39: 4264 | E39: 004/005 | F39: PETROLLUZ MATERIAIS ELETRICOS LTDA | G39: 02.493.174/0001-69 | H39: 2028 | I39: 46036 | J39: OPERADO | K39: H8 | L39: 46025 | M39: =IF(Tabela4[[#This Row],[RECOMPRADO]]="RECEBIDO","LIQUIDADO",IF(O39="LIQUIDADO","LIQUIDADO",IF(I39<$I$5,"VENCIDO","A VENCER"))) -> LIQUIDADO | N39: =IF(Tabela4[[#This Row],[STATUS]]="LIQUIDADO","",Tabela4[[#This Row],[VCTO]]-$I$5) | O39: LIQUIDADO
A40: LABOR | B40: 45986 | C40: NF | D40: 4265 | E40: 005/005 | F40: ELETROFLAVIO COMERCIAL ELETRICA LTDA | G40: 24.616.915/0001-94 | H40: 4152 | I40: 46044 | J40: OPERADO | K40: DEL MONTE | L40: 46003 | M40: =IF(Tabela4[[#This Row],[RECOMPRADO]]="RECEBIDO","LIQUIDADO",IF(O40="LIQUIDADO","LIQUIDADO",IF(I40<$I$5,"VENCIDO","A VENCER"))) -> LIQUIDADO | N40: =IF(Tabela4[[#This Row],[STATUS]]="LIQUIDADO","",Tabela4[[#This Row],[VCTO]]-$I$5) | O40: LIQUIDADO
A41: ALUFORCE | B41: 45986 | C41: NF | D41: 201 | E41: 003/004 | F41: GASPARZINHO DISTRIBUIDORA DE MATERIAIS ELETRICOS LTDA | G41: 2.042.020/0001-50 | H41: 1312.5 | I41: 46030 | J41: OPERADO | K41: H8 | L41: 46025 | M41: =IF(Tabela4[[#This Row],[RECOMPRADO]]="RECEBIDO","LIQUIDADO",IF(O41="LIQUIDADO","LIQUIDADO",IF(I41<$I$5,"VENCIDO","A VENCER"))) -> LIQUIDADO | N41: =IF(Tabela4[[#This Row],[STATUS]]="LIQUIDADO","",Tabela4[[#This Row],[VCTO]]-$I$5) | O41: LIQUIDADO
A42: ALUFORCE | B42: 45986 | C42: F9 | D42: 201 | E42: 003/004 | F42: GASPARZINHO DISTRIBUIDORA DE MATERIAIS ELETRICOS LTDA | G42: 2.042.020/0001-50 | H42: 1312.5 | I42: 46030 | J42: OPERADO | K42: H8 | L42: 46025 | M42: =IF(Tabela4[[#This Row],[RECOMPRADO]]="RECEBIDO","LIQUIDADO",IF(O42="LIQUIDADO","LIQUIDADO",IF(I42<$I$5,"VENCIDO","A VENCER"))) -> LIQUIDADO | N42: =IF(Tabela4[[#This Row],[STATUS]]="LIQUIDADO","",Tabela4[[#This Row],[VCTO]]-$I$5) | O42: LIQUIDADO
A43: LABOR | B43: 45986 | C43: NF | D43: 4265 | E43: 003/005 | F43: ELETROFLAVIO COMERCIAL ELETRICA LTDA | G43: 24.616.915/0001-94 | H43: 4152 | I43: 46030 | J43: OPERADO | K43: DEL MONTE | L43: 46003 | M43: =IF(Tabela4[[#This Row],[RECOMPRADO]]="RECEBIDO","LIQUIDADO",IF(O43="LIQUIDADO","LIQUIDADO",IF(I43<$I$5,"VENCIDO","A VENCER"))) -> LIQUIDADO | N43: =IF(Tabela4[[#This Row],[STATUS]]="LIQUIDADO","",Tabela4[[#This Row],[VCTO]]-$I$5) | O43: LIQUIDADO
A44: ENERGY | B44: 45986 | C44: NF | D44: 666 | E44: 001/003 | F44: ELIAS HUNGRIA DA CRUZ DE WENCESLAU GUIMARAES | G44: 15511415000105 | H44: 1075 | I44: 46015 | J44: OPERADO | K44: DEL MONTE | L44: 46003 | M44: =IF(Tabela4[[#This Row],[RECOMPRADO]]="RECEBIDO","LIQUIDADO",IF(O44="LIQUIDADO","LIQUIDADO",IF(I44<$I$5,"VENCIDO","A VENCER"))) -> VENCIDO | N44: =IF(Tabela4[[#This Row],[STATUS]]="LIQUIDADO","",Tabela4[[#This Row],[VCTO]]-$I$5) -> -83 | S44: FUNDO | T44: Em contato com senhor Elias o mesmo informa que esta aguardando o valor atualizado pelo cartório para efetuar o pagamento
A45: ENERGY | B45: 45986 | C45: NF | D45: 666 | E45: 002/003 | F45: ELIAS HUNGRIA DA CRUZ DE WENCESLAU GUIMARAES | G45: 15511415000105 | H45: 1075 | I45: 46022 | J45: OPERADO | K45: DEL MONTE | L45: 46003 | M45: =IF(Tabela4[[#This Row],[RECOMPRADO]]="RECEBIDO","LIQUIDADO",IF(O45="LIQUIDADO","LIQUIDADO",IF(I45<$I$5,"VENCIDO","A VENCER"))) -> VENCIDO | N45: =IF(Tabela4[[#This Row],[STATUS]]="LIQUIDADO","",Tabela4[[#This Row],[VCTO]]-$I$5) -> -76 | S45: FUNDO | T45: Em contato com senhor Elias o mesmo informa que esta aguardando o valor atualizado pelo cartório para efetuar o pagamento
A46: ENERGY | B46: 45986 | C46: NF | D46: 666 | E46: 003/003 | F46: ELIAS HUNGRIA DA CRUZ DE WENCESLAU GUIMARAES | G46: 15511415000105 | H46: 1075 | I46: 46029 | J46: OPERADO | K46: DEL MONTE | L46: 46026 | M46: =IF(Tabela4[[#This Row],[RECOMPRADO]]="RECEBIDO","LIQUIDADO",IF(O46="LIQUIDADO","LIQUIDADO",IF(I46<$I$5,"VENCIDO","A VENCER"))) -> VENCIDO | N46: =IF(Tabela4[[#This Row],[STATUS]]="LIQUIDADO","",Tabela4[[#This Row],[VCTO]]-$I$5) -> -69 | S46: FUNDO | T46: Em contato com senhor Elias o mesmo informa que esta aguardando o valor atualizado pelo cartório para efetuar o pagamento
A47: ALUFORCE | B47: 45986 | C47: NF | D47: 201 | E47: 004/004 | F47: GASPARZINHO DISTRIBUIDORA DE MATERIAIS ELETRICOS LTDA | G47: 2.042.020/0001-50 | H47: 1312.5 | I47: 46037 | J47: OPERADO | K47: H8 | L47: 46025 | M47: =IF(Tabela4[[#This Row],[RECOMPRADO]]="RECEBIDO","LIQUIDADO",IF(O47="LIQUIDADO","LIQUIDADO",IF(I47<$I$5,"VENCIDO","A VENCER"))) -> LIQUIDADO | N47: =IF(Tabela4[[#This Row],[STATUS]]="LIQUIDADO","",Tabela4[[#This Row],[VCTO]]-$I$5) | O47: LIQUIDADO
A48: ALUFORCE | B48: 45986 | C48: F9 | D48: 201 | E48: 004/004 | F48: GASPARZINHO DISTRIBUIDORA DE MATERIAIS ELETRICOS LTDA | G48: 2.042.020/0001-50 | H48: 1312.5 | I48: 46037 | J48: OPERADO | K48: H8 | L48: 46025 | M48: =IF(Tabela4[[#This Row],[RECOMPRADO]]="RECEBIDO","LIQUIDADO",IF(O48="LIQUIDADO","LIQUIDADO",IF(I48<$I$5,"VENCIDO","A VENCER"))) -> LIQUIDADO | N48: =IF(Tabela4[[#This Row],[STATUS]]="LIQUIDADO","",Tabela4[[#This Row],[VCTO]]-$I$5) | O48: LIQUIDADO
A49: LABOR | B49: 45986 | C49: NF | D49: 4265 | E49: 004/005 | F49: ELETROFLAVIO COMERCIAL ELETRICA LTDA | G49: 24.616.915/0001-94 | H49: 4152 | I49: 46037 | J49: OPERADO | K49: DEL MONTE | L49: 46026 | M49: =IF(Tabela4[[#This Row],[RECOMPRADO]]="RECEBIDO","LIQUIDADO",IF(O49="LIQUIDADO","LIQUIDADO",IF(I49<$I$5,"VENCIDO","A VENCER"))) -> LIQUIDADO | N49: =IF(Tabela4[[#This Row],[STATUS]]="LIQUIDADO","",Tabela4[[#This Row],[VCTO]]-$I$5) | O49: LIQUIDADO
A50: ENERGY | B50: 45988 | C50: NF | D50: 671 | E50: 003/003 | F50: CONSORCIO SMART CITY SP | G50: 51.604.560/0001-96 | H50: 2058 | I50: 46030 | J50: OPERADO | K50: H8 | L50: 46025 | M50: =IF(Tabela4[[#This Row],[RECOMPRADO]]="RECEBIDO","LIQUIDADO",IF(O50="LIQUIDADO","LIQUIDADO",IF(I50<$I$5,"VENCIDO","A VENCER"))) -> LIQUIDADO | N50: =IF(Tabela4[[#This Row],[STATUS]]="LIQUIDADO","",Tabela4[[#This Row],[VCTO]]-$I$5) | O50: LIQUIDADO
A51: ENERGY | B51: 45988 | C51: NF | D51: 672 | E51: 003/003 | F51: CONSORCIO SMART CITY SP | G51: 51.604.560/0001-96 | H51: 377.3 | I51: 46030 | J51: OPERADO | K51: H8 | L51: 46025 | M51: =IF(Tabela4[[#This Row],[RECOMPRADO]]="RECEBIDO","LIQUIDADO",IF(O51="LIQUIDADO","LIQUIDADO",IF(I51<$I$5,"VENCIDO","A VENCER"))) -> LIQUIDADO | N51: =IF(Tabela4[[#This Row],[STATUS]]="LIQUIDADO","",Tabela4[[#This Row],[VCTO]]-$I$5) | O51: LIQUIDADO
A52: ALUFORCE | B52: 45989 | C52: NF | D52: 207 | E52: 001/001 | F52: ILUMINACAO PAULISTANA SPE S/A | G52: 29.851.606/0001-12 | H52: 15200 | I52: 46017 | J52: OPERADO | K52: H8 | L52: 46025 | M52: =IF(Tabela4[[#This Row],[RECOMPRADO]]="RECEBIDO","LIQUIDADO",IF(O52="LIQUIDADO","LIQUIDADO",IF(I52<$I$5,"VENCIDO","A VENCER"))) -> LIQUIDADO | N52: =IF(Tabela4[[#This Row],[STATUS]]="LIQUIDADO","",Tabela4[[#This Row],[VCTO]]-$I$5) | O52: LIQUIDADO
A53: ALUFORCE | B53: 45989 | C53: NF | D53: 208 | E53: 003/003 | F53: COMERCIAL MARTINS LTDA | G53: 20.891.953/0001-02 | H53: 1641.66 | I53: 46049 | J53: OPERADO | K53: H8 | L53: 46025 | M53: =IF(Tabela4[[#This Row],[RECOMPRADO]]="RECEBIDO","LIQUIDADO",IF(O53="LIQUIDADO","LIQUIDADO",IF(I53<$I$5,"VENCIDO","A VENCER"))) -> LIQUIDADO | N53: =IF(Tabela4[[#This Row],[STATUS]]="LIQUIDADO","",Tabela4[[#This Row],[VCTO]]-$I$5) | O53: LIQUIDADO
A54: ALUFORCE | B54: 45989 | C54: F9 | D54: 208 | E54: 003/003 | F54: COMERCIAL MARTINS LTDA | G54: 20.891.953/0001-02 | H54: 1641.66 | I54: 46049 | J54: OPERADO | K54: H8 | L54: 46025 | M54: =IF(Tabela4[[#This Row],[RECOMPRADO]]="RECEBIDO","LIQUIDADO",IF(O54="LIQUIDADO","LIQUIDADO",IF(I54<$I$5,"VENCIDO","A VENCER"))) -> LIQUIDADO | N54: =IF(Tabela4[[#This Row],[STATUS]]="LIQUIDADO","",Tabela4[[#This Row],[VCTO]]-$I$5) | O54: LIQUIDADO
A55: ALUFORCE | B55: 45989 | C55: NF | D55: 209 | E55: 003/003 | F55: CENTER LED MATERIAIS ELETRICOS LTDA | G55: 26.474.579/0001-18 | H55: 16349.71 | I55: 46041 | J55: OPERADO | K55: VALE RIO CLARO | L55: 46027 | M55: =IF(Tabela4[[#This Row],[RECOMPRADO]]="RECEBIDO","LIQUIDADO",IF(O55="LIQUIDADO","LIQUIDADO",IF(I55<$I$5,"VENCIDO","A VENCER"))) -> LIQUIDADO | N55: =IF(Tabela4[[#This Row],[STATUS]]="LIQUIDADO","",Tabela4[[#This Row],[VCTO]]-$I$5) | O55: LIQUIDADO
A56: ALUFORCE | B56: 45989 | C56: NF | D56: 210 | E56: 004/004 | F56: ELETRICA CASA FERREIRA LTDA | G56: 33.167.223/0001-05 | H56: 1056.25 | I56: 46041 | J56: OPERADO | K56: H8 | L56: 46025 | M56: =IF(Tabela4[[#This Row],[RECOMPRADO]]="RECEBIDO","LIQUIDADO",IF(O56="LIQUIDADO","LIQUIDADO",IF(I56<$I$5,"VENCIDO","A VENCER"))) -> LIQUIDADO | N56: =IF(Tabela4[[#This Row],[STATUS]]="LIQUIDADO","",Tabela4[[#This Row],[VCTO]]-$I$5) | O56: LIQUIDADO
A57: ALUFORCE | B57: 45989 | C57: F9 | D57: 210 | E57: 004/004 | F57: ELETRICA CASA FERREIRA LTDA | G57: 33.167.223/0001-05 | H57: 1056.25 | I57: 46041 | J57: OPERADO | K57: H8 | L57: 46025 | M57: =IF(Tabela4[[#This Row],[RECOMPRADO]]="RECEBIDO","LIQUIDADO",IF(O57="LIQUIDADO","LIQUIDADO",IF(I57<$I$5,"VENCIDO","A VENCER"))) -> LIQUIDADO | N57: =IF(Tabela4[[#This Row],[STATUS]]="LIQUIDADO","",Tabela4[[#This Row],[VCTO]]-$I$5) | O57: LIQUIDADO
A58: ALUFORCE | B58: 45989 | C58: NF | D58: 213 | E58: 004/004 | F58: FERLIN & ANDRADE MATERIAIS ELETRICOS LTDA | G58: 01.532.397/0001-25 | H58: 1111.88 | I58: 46049 | J58: OPERADO | K58: H8 | L58: 46025 | M58: =IF(Tabela4[[#This Row],[RECOMPRADO]]="RECEBIDO","LIQUIDADO",IF(O58="LIQUIDADO","LIQUIDADO",IF(I58<$I$5,"VENCIDO","A VENCER"))) -> LIQUIDADO | N58: =IF(Tabela4[[#This Row],[STATUS]]="LIQUIDADO","",Tabela4[[#This Row],[VCTO]]-$I$5) | O58: LIQUIDADO
... A80: ALUFORCE | B80: 45989 | C80: F9 | D80: 210 | E80: 003/004 | F80: ELETRICA CASA FERREIRA LTDA | G80: 33.167.223/0001-05 | H80: 1056.25 | I80: 46034 | J80: OPERADO | K80: H8 | L80: 46025 | M80: =IF(Tabela4[[#This Row],[RECOMPRADO]]="RECEBIDO","LIQUIDADO",IF(O80="LIQUIDADO","LIQUIDADO",IF(I80<$I$5,"VENCIDO","A VENCER"))) -> LIQUIDADO | N80: =IF(Tabela4[[#This Row],[STATUS]]="LIQUIDADO","",Tabela4[[#This Row],[VCTO]]-$I$5) | O80: LIQUIDADO
A81: ALUFORCE | B81: 45994 | C81: NF | D81: 217 | E81: 005 | F81: CABEDAL MATERIAIS ELETRICOS LTDA | G81: 09.232.518/0001-25 | H81: 673.6 | I81: 46044 | J81: OPERADO | K81: DEL MONTE | L81: 46026 | M81: LIQUIDADO | N81: =IF(Tabela4[[#This Row],[STATUS]]="LIQUIDADO","",Tabela4[[#This Row],[VCTO]]-$I$5) | O81: LIQUIDADO
A82: ENERGY | B82: 45994 | C82: NF | D82: 675 | E82: 003 | F82: ELETRIFICAR COMERCIO DE FERRAGENS FERRAMENTAS E PRODUTOS PA | G82: 14.650.232/0001-08 | H82: 2661.4 | I82: 46045 | J82: OPERADO | K82: DEL MONTE | L82: 46026 | M82: =IF(Tabela4[[#This Row],[RECOMPRADO]]="RECEBIDO","LIQUIDADO",IF(O82="LIQUIDADO","LIQUIDADO",IF(I82<$I$5,"VENCIDO","A VENCER"))) -> LIQUIDADO | N82: =IF(Tabela4[[#This Row],[STATUS]]="LIQUIDADO","",Tabela4[[#This Row],[VCTO]]-$I$5) | O82: LIQUIDADO
A83: ALUFORCE | B83: 45994 | C83: NF | D83: 217 | E83: 004 | F83: CABEDAL MATERIAIS ELETRICOS LTDA | G83: 09.232.518/0001-25 | H83: 673.6 | I83: 46037 | J83: OPERADO | K83: DEL MONTE | L83: 46026 | M83: =IF(Tabela4[[#This Row],[RECOMPRADO]]="RECEBIDO","LIQUIDADO",IF(O83="LIQUIDADO","LIQUIDADO",IF(I83<$I$5,"VENCIDO","A VENCER"))) -> LIQUIDADO | N83: =IF(Tabela4[[#This Row],[STATUS]]="LIQUIDADO","",Tabela4[[#This Row],[VCTO]]-$I$5) | O83: LIQUIDADO
A84: ALUFORCE | B84: 45994 | C84: NF | D84: 218 | E84: 003 | F84: L P MARINHO MATERIAIS ELETRICOS LTDA | G84: 36.108.548/0001-05 | H84: 2021.66 | I84: 46037 | J84: OPERADO | K84: DEL MONTE | L84: 46026 | M84: =IF(Tabela4[[#This Row],[RECOMPRADO]]="RECEBIDO","LIQUIDADO",IF(O84="LIQUIDADO","LIQUIDADO",IF(I84<$I$5,"VENCIDO","A VENCER"))) -> LIQUIDADO | N84: =IF(Tabela4[[#This Row],[STATUS]]="LIQUIDADO","",Tabela4[[#This Row],[VCTO]]-$I$5) | O84: LIQUIDADO
A85: ENERGY | B85: 45994 | C85: NF | D85: 675 | E85: 002 | F85: ELETRIFICAR COMERCIO DE FERRAGENS FERRAMENTAS E PRODUTOS PA | G85: 14.650.232/0001-08 | H85: 2661.4 | I85: 46034 | J85: OPERADO | K85: DEL MONTE | L85: 46026 | M85: =IF(Tabela4[[#This Row],[RECOMPRADO]]="RECEBIDO","LIQUIDADO",IF(O85="LIQUIDADO","LIQUIDADO",IF(I85<$I$5,"VENCIDO","A VENCER"))) -> LIQUIDADO | N85: =IF(Tabela4[[#This Row],[STATUS]]="LIQUIDADO","",Tabela4[[#This Row],[VCTO]]-$I$5) | O85: LIQUIDADO
A86: ALUFORCE | B86: 45994 | C86: NF | D86: 217 | E86: 003 | F86: CABEDAL MATERIAIS ELETRICOS LTDA | G86: 09.232.518/0001-25 | H86: 673.6 | I86: 46030 | J86: OPERADO | K86: DEL MONTE | L86: 46026 | M86: =IF(Tabela4[[#This Row],[RECOMPRADO]]="RECEBIDO","LIQUIDADO",IF(O86="LIQUIDADO","LIQUIDADO",IF(I86<$I$5,"VENCIDO","A VENCER"))) -> LIQUIDADO | N86: =IF(Tabela4[[#This Row],[STATUS]]="LIQUIDADO","",Tabela4[[#This Row],[VCTO]]-$I$5) | O86: LIQUIDADO
A87: ALUFORCE | B87: 45994 | C87: NF | D87: 218 | E87: 002 | F87: L P MARINHO MATERIAIS ELETRICOS LTDA | G87: 36.108.548/0001-05 | H87: 2021.67 | I87: 46030 | J87: OPERADO | K87: DEL MONTE | L87: 46026 | M87: =IF(Tabela4[[#This Row],[RECOMPRADO]]="RECEBIDO","LIQUIDADO",IF(O87="LIQUIDADO","LIQUIDADO",IF(I87<$I$5,"VENCIDO","A VENCER"))) -> LIQUIDADO | N87: =IF(Tabela4[[#This Row],[STATUS]]="LIQUIDADO","",Tabela4[[#This Row],[VCTO]]-$I$5) | O87: LIQUIDADO
A88: ENERGY | B88: 45994 | C88: NF | D88: 675 | E88: 001 | F88: ELETRIFICAR COMERCIO DE FERRAGENS FERRAMENTAS E PRODUTOS PA | G88: 14.650.232/0001-08 | H88: 3466.2 | I88: 46027 | J88: OPERADO | K88: DEL MONTE | L88: 46026 | M88: =IF(Tabela4[[#This Row],[RECOMPRADO]]="RECEBIDO","LIQUIDADO",IF(O88="LIQUIDADO","LIQUIDADO",IF(I88<$I$5,"VENCIDO","A VENCER"))) -> LIQUIDADO | N88: =IF(Tabela4[[#This Row],[STATUS]]="LIQUIDADO","",Tabela4[[#This Row],[VCTO]]-$I$5) | O88: LIQUIDADO
A89: ENERGY | B89: 45994 | C89: NF | D89: 674 | E89: 001 | F89: CONSORCIO ALQUES - J.N.R | G89: 55.060.017/0001-26 | H89: 15000 | I89: 46048 | J89: OPERADO | K89: DEL MONTE | L89: 46026 | M89: =IF(Tabela4[[#This Row],[RECOMPRADO]]="RECEBIDO","LIQUIDADO",IF(O89="LIQUIDADO","LIQUIDADO",IF(I89<$I$5,"VENCIDO","A VENCER"))) -> LIQUIDADO | N89: =IF(Tabela4[[#This Row],[STATUS]]="LIQUIDADO","",Tabela4[[#This Row],[VCTO]]-$I$5) | O89: LIQUIDADO
A90: ENERGY | B90: 45994 | C90: NF | D90: 676 | E90: 002 | F90: MCFEE CONSTRUCOES E ELETRIFICAÇOES LTDA | G90: 22.991.072/0001-80 | H90: 1962.5 | I90: 46034 | J90: OPERADO | K90: FAMA | L90: 46037 | M90: =IF(Tabela4[[#This Row],[RECOMPRADO]]="RECEBIDO","LIQUIDADO",IF(O90="LIQUIDADO","LIQUIDADO",IF(I90<$I$5,"VENCIDO","A VENCER"))) -> LIQUIDADO | N90: =IF(Tabela4[[#This Row],[STATUS]]="LIQUIDADO","",Tabela4[[#This Row],[VCTO]]-$I$5) | O90: LIQUIDADO
A91: ENERGY | B91: 45994 | C91: NF | D91: 677 | E91: 002 | F91: MENG ENGENHARIA COMERCIO E INDUSTRIA LTDA. | G91: 49.670.524/0001-89 | H91: 5850 | I91: 46034 | J91: OPERADO | K91: FAMA | L91: 46037 | M91: =IF(Tabela4[[#This Row],[RECOMPRADO]]="RECEBIDO","LIQUIDADO",IF(O91="LIQUIDADO","LIQUIDADO",IF(I91<$I$5,"VENCIDO","A VENCER"))) -> LIQUIDADO | N91: =IF(Tabela4[[#This Row],[STATUS]]="LIQUIDADO","",Tabela4[[#This Row],[VCTO]]-$I$5) | O91: LIQUIDADO
A92: ENERGY | B92: 45994 | C92: NF | D92: 676 | E92: 001 | F92: MCFEE CONSTRUCOES E ELETRIFICAÇOES LTDA | G92: 22.991.072/0001-80 | H92: 2536.89 | I92: 46027 | J92: OPERADO | K92: FAMA | L92: 46037 | M92: =IF(Tabela4[[#This Row],[RECOMPRADO]]="RECEBIDO","LIQUIDADO",IF(O92="LIQUIDADO","LIQUIDADO",IF(I92<$I$5,"VENCIDO","A VENCER"))) -> LIQUIDADO | N92: =IF(Tabela4[[#This Row],[STATUS]]="LIQUIDADO","",Tabela4[[#This Row],[VCTO]]-$I$5) | O92: LIQUIDADO
A93: ALUFORCE | B93: 45994 | C93: NF | D93: 217 | E93: 005 | F93: CABEDAL MATERIAIS ELETRICOS LTDA | G93: 09.232.518/0001-25 | H93: 673.6 | I93: 46044 | J93: OPERADO | K93: H8 | L93: 46025 | M93: =IF(Tabela4[[#This Row],[RECOMPRADO]]="RECEBIDO","LIQUIDADO",IF(O93="LIQUIDADO","LIQUIDADO",IF(I93<$I$5,"VENCIDO","A VENCER"))) -> LIQUIDADO | N93: =IF(Tabela4[[#This Row],[STATUS]]="LIQUIDADO","",Tabela4[[#This Row],[VCTO]]-$I$5) | O93: LIQUIDADO
... A100: ENERGY | B100: 45994 | C100: NF | D100: 675 | E100: 001 | F100: ELETRIFICAR COMERCIO DE FERRAGENS FERRAMENTAS E PRODUTOS PA | G100: 14.650.232/0001-08 | H100: 2661.4 | I100: 46052 | J100: OPERADO | K100: DEL MONTE | L100: 46026 | M100: =IF(Tabela4[[#This Row],[RECOMPRADO]]="RECEBIDO","LIQUIDADO",IF(O100="LIQUIDADO","LIQUIDADO",IF(I100<$I$5,"VENCIDO","A VENCER"))) -> LIQUIDADO | N100: =IF(Tabela4[[#This Row],[STATUS]]="LIQUIDADO","",Tabela4[[#This Row],[VCTO]]-$I$5) | O100: LIQUIDADO
A101: ALUFORCE | B101: 45994 | C101: NF | D101: 220 | E101: 003 | F101: ELETROREDE LTDA | G101: 53.268.333/0001-62 | H101: 812.04 | I101: 46059 | J101: OPERADO | K101: H8 | L101: 46025 | M101: =IF(Tabela4[[#This Row],[RECOMPRADO]]="RECEBIDO","LIQUIDADO",IF(O101="LIQUIDADO","LIQUIDADO",IF(I101<$I$5,"VENCIDO","A VENCER"))) -> LIQUIDADO | N101: =IF(Tabela4[[#This Row],[STATUS]]="LIQUIDADO","",Tabela4[[#This Row],[VCTO]]-$I$5) | O101: LIQUIDADO
A102: ALUFORCE | B102: 45994 | C102: F9 | D102: 220 | E102: 003 | F102: ELETROREDE LTDA | G102: 53.268.333/0001-62 | H102: 756.68 | I102: 46059 | J102: OPERADO | K102: H8 | L102: 46025 | M102: =IF(Tabela4[[#This Row],[RECOMPRADO]]="RECEBIDO","LIQUIDADO",IF(O102="LIQUIDADO","LIQUIDADO",IF(I102<$I$5,"VENCIDO","A VENCER"))) -> LIQUIDADO | N102: =IF(Tabela4[[#This Row],[STATUS]]="LIQUIDADO","",Tabela4[[#This Row],[VCTO]]-$I$5) | O102: LIQUIDADO | T102: CLIENTE VAI EFETUAR PAGAMENTO HOJE
A103: ALUFORCE | B103: 45996 | C103: NF | D103: 221 | E103: 002 | F103: LF ELETRIFICACOES LTDA | G103: 28.876.680/0001-20 | H103: 1685 | I103: 46041 | J103: OPERADO | K103: H8 | L103: 46025 | M103: =IF(Tabela4[[#This Row],[RECOMPRADO]]="RECEBIDO","LIQUIDADO",IF(O103="LIQUIDADO","LIQUIDADO",IF(I103<$I$5,"VENCIDO","A VENCER"))) -> LIQUIDADO | N103: =IF(Tabela4[[#This Row],[STATUS]]="LIQUIDADO","",Tabela4[[#This Row],[VCTO]]-$I$5) | O103: LIQUIDADO
A104: ALUFORCE | B104: 45996 | C104: F9 | D104: 221 | E104: 002 | F104: LF ELETRIFICACOES LTDA | G104: 28.876.680/0001-20 | H104: 1685 | I104: 46041 | J104: OPERADO | K104: H8 | L104: 46025 | M104: =IF(Tabela4[[#This Row],[RECOMPRADO]]="RECEBIDO","LIQUIDADO",IF(O104="LIQUIDADO","LIQUIDADO",IF(I104<$I$5,"VENCIDO","A VENCER"))) -> LIQUIDADO | N104: =IF(Tabela4[[#This Row],[STATUS]]="LIQUIDADO","",Tabela4[[#This Row],[VCTO]]-$I$5) | O104: LIQUIDADO
A105: ALUFORCE | B105: 45996 | C105: NF | D105: 226 | E105: 004 | F105: COMERCIAL ELETRICA PAPIRO LTDA | G105: 27.368.821/0001-31 | H105: 1094.5 | I105: 46041 | J105: OPERADO | K105: H8 | L105: 46025 | M105: =IF(Tabela4[[#This Row],[RECOMPRADO]]="RECEBIDO","LIQUIDADO",IF(O105="LIQUIDADO","LIQUIDADO",IF(I105<$I$5,"VENCIDO","A VENCER"))) -> LIQUIDADO | N105: =IF(Tabela4[[#This Row],[STATUS]]="LIQUIDADO","",Tabela4[[#This Row],[VCTO]]-$I$5) | O105: LIQUIDADO
A106: ALUFORCE | B106: 45996 | C106: NF | D106: 226 | E106: 005 | F106: COMERCIAL ELETRICA PAPIRO LTDA | G106: 27.368.821/0001-31 | H106: 1094.5 | I106: 46048 | J106: OPERADO | K106: H8 | L106: 46025 | M106: =IF(Tabela4[[#This Row],[RECOMPRADO]]="RECEBIDO","LIQUIDADO",IF(O106="LIQUIDADO","LIQUIDADO",IF(I106<$I$5,"VENCIDO","A VENCER"))) -> LIQUIDADO | N106: =IF(Tabela4[[#This Row],[STATUS]]="LIQUIDADO","",Tabela4[[#This Row],[VCTO]]-$I$5) | O106: LIQUIDADO
A107: ALUFORCE | B107: 45996 | C107: F9 | D107: 226 | E107: 004 | F107: COMERCIAL ELETRICA PAPIRO LTDA | G107: 27.368.821/0001-31 | H107: 1094.5 | I107: 46041 | J107: OPERADO | K107: H8 | L107: 46025 | M107: =IF(Tabela4[[#This Row],[RECOMPRADO]]="RECEBIDO","LIQUIDADO",IF(O107="LIQUIDADO","LIQUIDADO",IF(I107<$I$5,"VENCIDO","A VENCER"))) -> LIQUIDADO | N107: =IF(Tabela4[[#This Row],[STATUS]]="LIQUIDADO","",Tabela4[[#This Row],[VCTO]]-$I$5) | O107: LIQUIDADO
A108: ALUFORCE | B108: 45996 | C108: F9 | D108: 226 | E108: 005 | F108: COMERCIAL ELETRICA PAPIRO LTDA | G108: 27.368.821/0001-31 | H108: 1094.5 | I108: 46048 | J108: OPERADO | K108: H8 | L108: 46025 | M108: =IF(Tabela4[[#This Row],[RECOMPRADO]]="RECEBIDO","LIQUIDADO",IF(O108="LIQUIDADO","LIQUIDADO",IF(I108<$I$5,"VENCIDO","A VENCER"))) -> LIQUIDADO | N108: =IF(Tabela4[[#This Row],[STATUS]]="LIQUIDADO","",Tabela4[[#This Row],[VCTO]]-$I$5) | O108: LIQUIDADO
A109: LABOR | B109: 45996 | C109: NF | D109: 4269 | E109: 003 | F109: IM CONDUTORES ELETRICOS LTDA | G109: 30.525.936/0001-05 | H109: 594.38 | I109: 46041 | J109: OPERADO | K109: H8 | L109: 46025 | M109: =IF(Tabela4[[#This Row],[RECOMPRADO]]="RECEBIDO","LIQUIDADO",IF(O109="LIQUIDADO","LIQUIDADO",IF(I109<$I$5,"VENCIDO","A VENCER"))) -> LIQUIDADO | N109: =IF(Tabela4[[#This Row],[STATUS]]="LIQUIDADO","",Tabela4[[#This Row],[VCTO]]-$I$5) | O109: LIQUIDADO
A110: LABOR | B110: 45996 | C110: NF | D110: 4269 | E110: 004 | F110: IM CONDUTORES ELETRICOS LTDA | G110: 30.525.936/0001-05 | H110: 594.36 | I110: 46048 | J110: OPERADO | K110: H8 | L110: 46025 | M110: =IF(Tabela4[[#This Row],[RECOMPRADO]]="RECEBIDO","LIQUIDADO",IF(O110="LIQUIDADO","LIQUIDADO",IF(I110<$I$5,"VENCIDO","A VENCER"))) -> LIQUIDADO | N110: =IF(Tabela4[[#This Row],[STATUS]]="LIQUIDADO","",Tabela4[[#This Row],[VCTO]]-$I$5) | O110: LIQUIDADO
A111: LABOR | B111: 45996 | C111: F9 | D111: 4269 | E111: 003 | F111: IM CONDUTORES ELETRICOS LTDA | G111: 30.525.936/0001-05 | H111: 594.38 | I111: 46041 | J111: OPERADO | K111: H8 | L111: 46025 | M111: =IF(Tabela4[[#This Row],[RECOMPRADO]]="RECEBIDO","LIQUIDADO",IF(O111="LIQUIDADO","LIQUIDADO",IF(I111<$I$5,"VENCIDO","A VENCER"))) -> LIQUIDADO | N111: =IF(Tabela4[[#This Row],[STATUS]]="LIQUIDADO","",Tabela4[[#This Row],[VCTO]]-$I$5) | O111: LIQUIDADO
A112: LABOR | B112: 45996 | C112: F9 | D112: 4269 | E112: 004 | F112: IM CONDUTORES ELETRICOS LTDA | G112: 30.525.936/0001-05 | H112: 594.36 | I112: 46048 | J112: OPERADO | K112: H8 | L112: 46025 | M112: =IF(Tabela4[[#This Row],[RECOMPRADO]]="RECEBIDO","LIQUIDADO",IF(O112="LIQUIDADO","LIQUIDADO",IF(I112<$I$5,"VENCIDO","A VENCER"))) -> LIQUIDADO | N112: =IF(Tabela4[[#This Row],[STATUS]]="LIQUIDADO","",Tabela4[[#This Row],[VCTO]]-$I$5) | O112: LIQUIDADO
A113: LABOR | B113: 45996 | C113: NF | D113: 4270 | E113: 003 | F113: R.A. MATERIAIS ELETRICOS E DECORACOES LTDA | G113: 12.659.075/0001-68 | H113: 1402 | I113: 46041 | J113: OPERADO | K113: H8 | L113: 46025 | M113: =IF(Tabela4[[#This Row],[RECOMPRADO]]="RECEBIDO","LIQUIDADO",IF(O113="LIQUIDADO","LIQUIDADO",IF(I113<$I$5,"VENCIDO","A VENCER"))) -> LIQUIDADO | N113: =IF(Tabela4[[#This Row],[STATUS]]="LIQUIDADO","",Tabela4[[#This Row],[VCTO]]-$I$5) | O113: LIQUIDADO
A114: LABOR | B114: 45996 | C114: NF | D114: 4270 | E114: 004 | F114: R.A. MATERIAIS ELETRICOS E DECORACOES LTDA | G114: 12.659.075/0001-68 | H114: 1402 | I114: 46048 | J114: OPERADO | K114: H8 | L114: 46025 | M114: =IF(Tabela4[[#This Row],[RECOMPRADO]]="RECEBIDO","LIQUIDADO",IF(O114="LIQUIDADO","LIQUIDADO",IF(I114<$I$5,"VENCIDO","A VENCER"))) -> LIQUIDADO | N114: =IF(Tabela4[[#This Row],[STATUS]]="LIQUIDADO","",Tabela4[[#This Row],[VCTO]]-$I$5) | O114: LIQUIDADO
... A136: ALUFORCE | B136: 46000 | C136: NF | D136: 230 | E136: 002 | F136: ENERGIZE COMERCIO E SERVICOS DE MATERIAIS ELETRICOS LTDA | G136: 50.160.305/0001-39 | H136: 701.67 | I136: 46035 | J136: OPERADO | K136: H8 | L136: 46025 | M136: =IF(Tabela4[[#This Row],[RECOMPRADO]]="RECEBIDO","LIQUIDADO",IF(O136="LIQUIDADO","LIQUIDADO",IF(I136<$I$5,"VENCIDO","A VENCER"))) -> LIQUIDADO | N136: =IF(Tabela4[[#This Row],[STATUS]]="LIQUIDADO","",Tabela4[[#This Row],[VCTO]]-$I$5) | O136: LIQUIDADO
A137: ALUFORCE | B137: 46000 | C137: NF | D137: 229 | E137: 001 | F137: STOPAR HOLDING LTDA | G137: 28477616000103 | H137: 60018.48 | I137: 46028 | J137: OPERADO | K137: DEL MONTE | L137: 46026 | M137: =IF(Tabela4[[#This Row],[RECOMPRADO]]="RECEBIDO","LIQUIDADO",IF(O137="LIQUIDADO","LIQUIDADO",IF(I137<$I$5,"VENCIDO","A VENCER"))) -> LIQUIDADO | N137: =IF(Tabela4[[#This Row],[STATUS]]="LIQUIDADO","",Tabela4[[#This Row],[VCTO]]-$I$5) | O137: LIQUIDADO
A138: ENERGY | B138: 46001 | C138: NF | D138: 686 | E138: 004 | F138: IGREJA ANGLICANA ESPERANCA | G138: 27686833000104 | H138: 1400 | I138: 46043 | J138: OPERADO | K138: DEL MONTE | L138: 46026 | M138: =IF(Tabela4[[#This Row],[RECOMPRADO]]="RECEBIDO","LIQUIDADO",IF(O138="LIQUIDADO","LIQUIDADO",IF(I138<$I$5,"VENCIDO","A VENCER"))) -> LIQUIDADO | N138: =IF(Tabela4[[#This Row],[STATUS]]="LIQUIDADO","",Tabela4[[#This Row],[VCTO]]-$I$5) | O138: LIQUIDADO | S138: FUNDO | T138: Liquidação em cartório
A139: ENERGY | B139: 46001 | C139: NF | D139: 686 | E139: 003 | F139: IGREJA ANGLICANA ESPERANCA | G139: 27686833000104 | H139: 1400 | I139: 46036 | J139: OPERADO | K139: DEL MONTE | L139: 46026 | M139: =IF(Tabela4[[#This Row],[RECOMPRADO]]="RECEBIDO","LIQUIDADO",IF(O139="LIQUIDADO","LIQUIDADO",IF(I139<$I$5,"VENCIDO","A VENCER"))) -> LIQUIDADO | N139: =IF(Tabela4[[#This Row],[STATUS]]="LIQUIDADO","",Tabela4[[#This Row],[VCTO]]-$I$5) | O139: LIQUIDADO
A140: ALUFORCE | B140: 46002 | C140: NF | D140: 232 | E140: 003 | F140: LUZ ATUAL ILUMINACAO LTDA | G140: 20.112.049/0001-43 | H140: 1320 | I140: 46044 | J140: OPERADO | K140: DEL MONTE | L140: 46026 | M140: =IF(Tabela4[[#This Row],[RECOMPRADO]]="RECEBIDO","LIQUIDADO",IF(O140="LIQUIDADO","LIQUIDADO",IF(I140<$I$5,"VENCIDO","A VENCER"))) -> LIQUIDADO | N140: =IF(Tabela4[[#This Row],[STATUS]]="LIQUIDADO","",Tabela4[[#This Row],[VCTO]]-$I$5) | O140: LIQUIDADO
A141: ALUFORCE | B141: 46002 | C141: F9 | D141: 232 | E141: 003 | F141: LUZ ATUAL ILUMINACAO LTDA | G141: 20.112.049/0001-43 | H141: 1320 | I141: 46044 | J141: OPERADO | K141: DEL MONTE | L141: 46026 | M141: =IF(Tabela4[[#This Row],[RECOMPRADO]]="RECEBIDO","LIQUIDADO",IF(O141="LIQUIDADO","LIQUIDADO",IF(I141<$I$5,"VENCIDO","A VENCER"))) -> LIQUIDADO | N141: =IF(Tabela4[[#This Row],[STATUS]]="LIQUIDADO","",Tabela4[[#This Row],[VCTO]]-$I$5) | O141: LIQUIDADO
A142: ALUFORCE | B142: 46002 | C142: NF | D142: 233 | E142: 001 | F142: COMERCIAL MARTINS LTDA | G142: 20891953000102 | H142: 1920 | I142: 46048 | J142: OPERADO | K142: DEL MONTE | L142: 46026 | M142: =IF(Tabela4[[#This Row],[RECOMPRADO]]="RECEBIDO","LIQUIDADO",IF(O142="LIQUIDADO","LIQUIDADO",IF(I142<$I$5,"VENCIDO","A VENCER"))) -> LIQUIDADO | N142: =IF(Tabela4[[#This Row],[STATUS]]="LIQUIDADO","",Tabela4[[#This Row],[VCTO]]-$I$5) | O142: LIQUIDADO
A143: ALUFORCE | B143: 46002 | C143: NF | D143: 234 | E143: 002 | F143: MNS MOREIRA COMERCIO DE ILUMINACAO LTDA | G143: 08.752.660/0001-30 | H143: 2170 | I143: 46041 | J143: OPERADO | K143: DEL MONTE | L143: 46026 | M143: =IF(Tabela4[[#This Row],[RECOMPRADO]]="RECEBIDO","LIQUIDADO",IF(O143="LIQUIDADO","LIQUIDADO",IF(I143<$I$5,"VENCIDO","A VENCER"))) -> LIQUIDADO | N143: =IF(Tabela4[[#This Row],[STATUS]]="LIQUIDADO","",Tabela4[[#This Row],[VCTO]]-$I$5) | O143: LIQUIDADO
A144: ALUFORCE | B144: 46002 | C144: NF | D144: 234 | E144: 003 | F144: MNS MOREIRA COMERCIO DE ILUMINACAO LTDA | G144: 08.752.660/0001-30 | H144: 2170 | I144: 46043 | J144: OPERADO | K144: DEL MONTE | L144: 46026 | M144: =IF(Tabela4[[#This Row],[RECOMPRADO]]="RECEBIDO","LIQUIDADO",IF(O144="LIQUIDADO","LIQUIDADO",IF(I144<$I$5,"VENCIDO","A VENCER"))) -> LIQUIDADO | N144: =IF(Tabela4[[#This Row],[STATUS]]="LIQUIDADO","",Tabela4[[#This Row],[VCTO]]-$I$5) | O144: LIQUIDADO
A145: ALUFORCE | B145: 46002 | C145: NF | D145: 234 | E145: 001 | F145: MNS MOREIRA COMERCIO DE ILUMINACAO LTDA | G145: 08.752.660/0001-30 | H145: 2170 | I145: 46034 | J145: OPERADO | K145: DEL MONTE | L145: 46026 | M145: =IF(Tabela4[[#This Row],[RECOMPRADO]]="RECEBIDO","LIQUIDADO",IF(O145="LIQUIDADO","LIQUIDADO",IF(I145<$I$5,"VENCIDO","A VENCER"))) -> LIQUIDADO | N145: =IF(Tabela4[[#This Row],[STATUS]]="LIQUIDADO","",Tabela4[[#This Row],[VCTO]]-$I$5) | O145: LIQUIDADO
A146: ENERGY | B146: 46002 | C146: NF | D146: 690 | E146: 003 | F146: M.S. COMERCIO DE MATERIAIS E MANUTENCOES ELETRICAS LTDA | G146: 04.528.571/0001-54 | H146: 3122.5 | I146: 46045 | J146: OPERADO | K146: DEL MONTE | L146: 46026 | M146: =IF(Tabela4[[#This Row],[RECOMPRADO]]="RECEBIDO","LIQUIDADO",IF(O146="LIQUIDADO","LIQUIDADO",IF(I146<$I$5,"VENCIDO","A VENCER"))) -> LIQUIDADO | N146: =IF(Tabela4[[#This Row],[STATUS]]="LIQUIDADO","",Tabela4[[#This Row],[VCTO]]-$I$5) | O146: LIQUIDADO
A147: ALUFORCE | B147: 46002 | C147: NF | D147: 232 | E147: 002 | F147: LUZ ATUAL ILUMINACAO LTDA | G147: 20.112.049/0001-43 | H147: 1320 | I147: 46037 | J147: OPERADO | K147: DEL MONTE | L147: 46026 | M147: =IF(Tabela4[[#This Row],[RECOMPRADO]]="RECEBIDO","LIQUIDADO",IF(O147="LIQUIDADO","LIQUIDADO",IF(I147<$I$5,"VENCIDO","A VENCER"))) -> LIQUIDADO | N147: =IF(Tabela4[[#This Row],[STATUS]]="LIQUIDADO","",Tabela4[[#This Row],[VCTO]]-$I$5) | O147: LIQUIDADO
A148: ENERGY | B148: 46002 | C148: NF | D148: 690 | E148: 001 | F148: M.S. COMERCIO DE MATERIAIS E MANUTENCOES ELETRICAS LTDA | G148: 04.528.571/0001-54 | H148: 3122.5 | I148: 46031 | J148: OPERADO | K148: DEL MONTE | L148: 46026 | M148: =IF(Tabela4[[#This Row],[RECOMPRADO]]="RECEBIDO","LIQUIDADO",IF(O148="LIQUIDADO","LIQUIDADO",IF(I148<$I$5,"VENCIDO","A VENCER"))) -> LIQUIDADO | N148: =IF(Tabela4[[#This Row],[STATUS]]="LIQUIDADO","",Tabela4[[#This Row],[VCTO]]-$I$5) | O148: LIQUIDADO
A149: ALUFORCE | B149: 46002 | C149: NF | D149: 232 | E149: 001 | F149: LUZ ATUAL ILUMINACAO LTDA | G149: 20.112.049/0001-43 | H149: 1619.38 | I149: 46044 | J149: OPERADO | K149: DEL MONTE | L149: 46026 | M149: =IF(Tabela4[[#This Row],[RECOMPRADO]]="RECEBIDO","LIQUIDADO",IF(O149="LIQUIDADO","LIQUIDADO",IF(I149<$I$5,"VENCIDO","A VENCER"))) -> LIQUIDADO | N149: =IF(Tabela4[[#This Row],[STATUS]]="LIQUIDADO","",Tabela4[[#This Row],[VCTO]]-$I$5) | O149: LIQUIDADO
A150: ENERGY | B150: 46002 | C150: NF | D150: 689 | E150: 001 | F150: SOCIEDADE DE BEBIDAS MALACARNE LTDA | G150: 91.639.724/0001-35 | H150: 3900 | I150: 46035 | J150: OPERADO | K150: DEL MONTE | L150: 46026 | M150: =IF(Tabela4[[#This Row],[RECOMPRADO]]="RECEBIDO","LIQUIDADO",IF(O150="LIQUIDADO","LIQUIDADO",IF(I150<$I$5,"VENCIDO","A VENCER"))) -> LIQUIDADO | N150: =IF(Tabela4[[#This Row],[STATUS]]="LIQUIDADO","",Tabela4[[#This Row],[VCTO]]-$I$5) | O150: LIQUIDADO
A151: ENERGY | B151: 46002 | C151: NF | D151: 690 | E151: 002 | F151: M.S. COMERCIO DE MATERIAIS E MANUTENCOES ELETRICAS LTDA | G151: 04.528.571/0001-54 | H151: 3122.5 | I151: 46038 | J151: OPERADO | K151: DEL MONTE | L151: 46026 | M151: =IF(Tabela4[[#This Row],[RECOMPRADO]]="RECEBIDO","LIQUIDADO",IF(O151="LIQUIDADO","LIQUIDADO",IF(I151<$I$5,"VENCIDO","A VENCER"))) -> LIQUIDADO | N151: =IF(Tabela4[[#This Row],[STATUS]]="LIQUIDADO","",Tabela4[[#This Row],[VCTO]]-$I$5) | O151: LIQUIDADO
A152: ALUFORCE | B152: 46002 | C152: NF | D152: 236 | E152: 001 | F152: ILUMINACAO PAULISTANA SPE S/A | G152: 29.851.606/0001-12 | H152: 49863.6 | I152: 46030 | J152: OPERADO | K152: FAMA | L152: 46037 | M152: =IF(Tabela4[[#This Row],[RECOMPRADO]]="RECEBIDO","LIQUIDADO",IF(O152="LIQUIDADO","LIQUIDADO",IF(I152<$I$5,"VENCIDO","A VENCER"))) -> LIQUIDADO | N152: =IF(Tabela4[[#This Row],[STATUS]]="LIQUIDADO","",Tabela4[[#This Row],[VCTO]]-$I$5) | O152: LIQUIDADO
...

Sheet DISPONÍVEL
A1: 3
D5: DISPONÍVEL
D6: EMPRESA | E6: NF | F6: F9 | G6: TOTAL
D7: ALUFORCE | E7: =SUMIFS(FATURAMENTO!$H:$H,FATURAMENTO!$C:$C,DISPONÍVEL!E6,FATURAMENTO!$A:$A,DISPONÍVEL!D7,FATURAMENTO!$J:$J,DISPONÍVEL!$D$5) -> 0 | F7: =SUMIFS(FATURAMENTO!$H:$H,FATURAMENTO!$C:$C,DISPONÍVEL!F6,FATURAMENTO!$A:$A,D7,FATURAMENTO!$J:$J,DISPONÍVEL!$D$5) -> 0 | G7: =E7+F7 -> 0
D8: ENERGY | E8: =SUMIFS(FATURAMENTO!$H:$H,FATURAMENTO!$C:$C,E6,FATURAMENTO!$A:$A,DISPONÍVEL!D8,FATURAMENTO!$J:$J,DISPONÍVEL!$D$5) -> 0 | F8: =SUMIFS(FATURAMENTO!$H:$H,FATURAMENTO!$C:$C,F6,FATURAMENTO!$A:$A,D8,FATURAMENTO!$J:$J,DISPONÍVEL!$D$5) -> 0 | G8: =E8+F8 -> 0
D9: LABOR | E9: =SUMIFS(FATURAMENTO!$H:$H,FATURAMENTO!$C:$C,E6,FATURAMENTO!$A:$A,DISPONÍVEL!D9,FATURAMENTO!$J:$J,DISPONÍVEL!$D$5) -> 0 | F9: =SUMIFS(FATURAMENTO!$H:$H,FATURAMENTO!$C:$C,F6,FATURAMENTO!$A:$A,D9,FATURAMENTO!$J:$J,DISPONÍVEL!$D$5) -> 0 | G9: =E9+F9 -> 0
E10: =SUM(E7:E9) -> 0 | F10: =SUM(F7:F9) -> 0 | G10: =E10+F10 -> 0

Sheet A RECEBER
D5: POSIÇÃO DOS FUNDOS/FIDCS
D6: PARCEIRO | E6: A VENCER | F6: VENCIDO | G6: TOTAL | I6: LIQUIDADO
D8: A VISTA | E8: =SUMIFS(FATURAMENTO!$H$8:$H$1048576,FATURAMENTO!$M$8:$M$1048576,'A RECEBER'!E$6,FATURAMENTO!$J$8:$J$1048576,'A RECEBER'!D8) -> 0 | F8: =SUMIFS(FATURAMENTO!$H$8:$H$1048576,FATURAMENTO!$M$8:$M$1048576,'A RECEBER'!F$6,FATURAMENTO!$J$8:$J$1048576,D8) -> 44000 | G8: =E8+F8 -> 44000 | I8: =SUMIFS(FATURAMENTO!$H$8:$H$1048576,FATURAMENTO!$M$8:$M$1048576,'A RECEBER'!I$6,FATURAMENTO!$J$8:$J$1048576,D8) -> 114119.24
D9: CARTEIRA | E9: =SUMIFS(FATURAMENTO!$H$8:$H$1048576,FATURAMENTO!$M$8:$M$1048576,'A RECEBER'!E$6,FATURAMENTO!$J$8:$J$1048576,'A RECEBER'!D9) -> 12405.01 | F9: =SUMIFS(FATURAMENTO!$H$8:$H$1048576,FATURAMENTO!$M$8:$M$1048576,'A RECEBER'!F$6,FATURAMENTO!$J$8:$J$1048576,D9) -> 24402.5 | G9: =E9+F9 -> 36807.51 | I9: =SUMIFS(FATURAMENTO!$H$8:$H$1048576,FATURAMENTO!$M$8:$M$1048576,'A RECEBER'!I$6,FATURAMENTO!$J$8:$J$1048576,D9) -> 33993.15

Sheet DIARIO
B4: CONTAS A RECEBER - DIÁRIO | F4: =D7+E7-FATURAMENTO!H5 -> -3653281.9
B7: HOJE | C7: VALOR | D7: =SUM(D9:D373) -> 2598752.5 | E7: =SUM(E9:E373) -> 166071.02
B8: =TODAY() -> 46098 | C8: DATA | D8: A VENCER | E8: VENCIDO
B9: =TEXT(C9,"dddd") -> quinta-feira | C9: 46023 | D9: =SUMIFS(FATURAMENTO!$H$8:$H$1048576,FATURAMENTO!$M$8:$M$1048576,DIARIO!D$8,FATURAMENTO!$I$8:$I$1048576,DIARIO!C9) -> 0 | E9: =SUMIFS(FATURAMENTO!$H$8:$H$1048576,FATURAMENTO!$M$8:$M$1048576,DIARIO!E$8,FATURAMENTO!$I$8:$I$1048576,C9) -> 0
B10: =TEXT(C10,"dddd") -> sexta-feira | C10: 46024 | D10: =SUMIFS(FATURAMENTO!$H$8:$H$1048576,FATURAMENTO!$M$8:$M$1048576,DIARIO!D$8,FATURAMENTO!$I$8:$I$1048576,DIARIO!C10) -> 0 | E10: =SUMIFS(FATURAMENTO!$H$8:$H$1048576,FATURAMENTO!$M$8:$M$1048576,DIARIO!E$8,FATURAMENTO!$I$8:$I$1048576,C10) -> 0
B11: =TEXT(C11,"dddd") -> sábado | C11: 46025 | D11: =SUMIFS(FATURAMENTO!$H$8:$H$1048576,FATURAMENTO!$M$8:$M$1048576,DIARIO!D$8,FATURAMENTO!$I$8:$I$1048576,DIARIO!C11) -> 0 | E11: =SUMIFS(FATURAMENTO!$H$8:$H$1048576,FATURAMENTO!$M$8:$M$1048576,DIARIO!E$8,FATURAMENTO!$I$8:$I$1048576,C11) -> 0
B12: =TEXT(C12,"dddd") -> domingo | C12: 46026 | D12: =SUMIFS(FATURAMENTO!$H$8:$H$1048576,FATURAMENTO!$M$8:$M$1048576,DIARIO!D$8,FATURAMENTO!$I$8:$I$1048576,DIARIO!C12) -> 0 | E12: =SUMIFS(FATURAMENTO!$H$8:$H$1048576,FATURAMENTO!$M$8:$M$1048576,DIARIO!E$8,FATURAMENTO!$I$8:$I$1048576,C12) -> 0
B13: =TEXT(C13,"dddd") -> segunda-feira | C13: 46027 | D13: =SUMIFS(FATURAMENTO!$H$8:$H$1048576,FATURAMENTO!$M$8:$M$1048576,DIARIO!D$8,FATURAMENTO!$I$8:$I$1048576,DIARIO!C13) -> 0 | E13: =SUMIFS(FATURAMENTO!$H$8:$H$1048576,FATURAMENTO!$M$8:$M$1048576,DIARIO!E$8,FATURAMENTO!$I$8:$I$1048576,C13) -> 5875
B14: =TEXT(C14,"dddd") -> terça-feira | C14: 46028 | D14: =SUMIFS(FATURAMENTO!$H$8:$H$1048576,FATURAMENTO!$M$8:$M$1048576,DIARIO!D$8,FATURAMENTO!$I$8:$I$1048576,DIARIO!C14) -> 0 | E14: =SUMIFS(FATURAMENTO!$H$8:$H$1048576,FATURAMENTO!$M$8:$M$1048576,DIARIO!E$8,FATURAMENTO!$I$8:$I$1048576,C14) -> 0
B15: =TEXT(C15,"dddd") -> quarta-feira | C15: 46029 | D15: =SUMIFS(FATURAMENTO!$H$8:$H$1048576,FATURAMENTO!$M$8:$M$1048576,DIARIO!D$8,FATURAMENTO!$I$8:$I$1048576,DIARIO!C15) -> 0 | E15: =SUMIFS(FATURAMENTO!$H$8:$H$1048576,FATURAMENTO!$M$8:$M$1048576,DIARIO!E$8,FATURAMENTO!$I$8:$I$1048576,C15) -> 1075
B16: =TEXT(C16,"dddd") -> quinta-feira | C16: 46030 | D16: =SUMIFS(FATURAMENTO!$H$8:$H$1048576,FATURAMENTO!$M$8:$M$1048576,DIARIO!D$8,FATURAMENTO!$I$8:$I$1048576,DIARIO!C16) -> 0 | E16: =SUMIFS(FATURAMENTO!$H$8:$H$1048576,FATURAMENTO!$M$8:$M$1048576,DIARIO!E$8,FATURAMENTO!$I$8:$I$1048576,C16) -> 0
B17: =TEXT(C17,"dddd") -> sexta-feira | C17: 46031 | D17: =SUMIFS(FATURAMENTO!$H$8:$H$1048576,FATURAMENTO!$M$8:$M$1048576,DIARIO!D$8,FATURAMENTO!$I$8:$I$1048576,DIARIO!C17) -> 0 | E17: =SUMIFS(FATURAMENTO!$H$8:$H$1048576,FATURAMENTO!$M$8:$M$1048576,DIARIO!E$8,FATURAMENTO!$I$8:$I$1048576,C17) -> 0
B18: =TEXT(C18,"dddd") -> sábado | C18: 46032 | D18: =SUMIFS(FATURAMENTO!$H$8:$H$1048576,FATURAMENTO!$M$8:$M$1048576,DIARIO!D$8,FATURAMENTO!$I$8:$I$1048576,DIARIO!C18) -> 0 | E18: =SUMIFS(FATURAMENTO!$H$8:$H$1048576,FATURAMENTO!$M$8:$M$1048576,DIARIO!E$8,FATURAMENTO!$I$8:$I$1048576,C18) -> 0
B19: =TEXT(C19,"dddd") -> domingo | C19: 46033 | D19: =SUMIFS(FATURAMENTO!$H$8:$H$1048576,FATURAMENTO!$M$8:$M$1048576,DIARIO!D$8,FATURAMENTO!$I$8:$I$1048576,DIARIO!C19) -> 0 | E19: =SUMIFS(FATURAMENTO!$H$8:$H$1048576,FATURAMENTO!$M$8:$M$1048576,DIARIO!E$8,FATURAMENTO!$I$8:$I$1048576,C19) -> 0
B20: =TEXT(C20,"dddd") -> segunda-feira | C20: 46034 | D20: =SUMIFS(FATURAMENTO!$H$8:$H$1048576,FATURAMENTO!$M$8:$M$1048576,DIARIO!D$8,FATURAMENTO!$I$8:$I$1048576,DIARIO!C20) -> 0 | E20: =SUMIFS(FATURAMENTO!$H$8:$H$1048576,FATURAMENTO!$M$8:$M$1048576,DIARIO!E$8,FATURAMENTO!$I$8:$I$1048576,C20) -> 0
... B373: =TEXT(C373,"dddd") -> quinta-feira | C373: 46387 | D373: =SUMIFS(FATURAMENTO!$H$8:$H$1048576,FATURAMENTO!$M$8:$M$1048576,DIARIO!D$8,FATURAMENTO!$I$8:$I$1048576,DIARIO!C373) -> 0 | E373: =SUMIFS(FATURAMENTO!$H$8:$H$1048576,FATURAMENTO!$M$8:$M$1048576,DIARIO!E$8,FATURAMENTO!$I$8:$I$1048576,C373) -> 0

Sheet FUNDOS
C5: POSIÇÃO DOS FUNDOS/FIDCS | J5: RECOMPRA | N5: CARTORIO
C6: PARCEIRO | D6: A VENCER | E6: VENCIDO | F6: TOTAL | H6: LIQUIDADO | J6: A RECEBER | K6: RECEBIDO | L6: TOTAL | N6: FUNDO | O6: ALUFORCE
C7: AUGURI | D7: =SUMIFS(FATURAMENTO!$H$8:$H$1048576,FATURAMENTO!$M$8:$M$1048576,FUNDOS!$D$6,FATURAMENTO!$K$8:$K$1048576,FUNDOS!C7) -> 150514.04 | E7: =SUMIFS(FATURAMENTO!$H$8:$H$1048576,FATURAMENTO!$M$8:$M$1048576,$E$6,FATURAMENTO!$K$8:$K$1048576,C7) -> 0 | F7: =D7+E7-L7 -> 150514.04 | H7: =SUMIFS(FATURAMENTO!$H$8:$H$1048576,FATURAMENTO!$M$8:$M$1048576,$H$6,FATURAMENTO!$K$8:$K$1048576,C7) -> 67217.11 | J7: =SUMIFS(FATURAMENTO!$H$8:$H$1048576,FATURAMENTO!$K$8:$K$1048576,FUNDOS!$C7,FATURAMENTO!$Q$8:$Q$1048576,FUNDOS!$J$6) -> 0 | K7: =SUMIFS(FATURAMENTO!$H$8:$H$1048576,FATURAMENTO!$K$8:$K$1048576,FUNDOS!$C7,FATURAMENTO!$Q$8:$Q$1048576,$K$6) -> 0 | L7: =J7 -> 0 | N7: =SUMIFS(FATURAMENTO!$H$8:$H$1048576,FATURAMENTO!$K$8:$K$1048576,FUNDOS!$C7,FATURAMENTO!$S$8:$S$1048576,FUNDOS!$N$6) -> 0 | O7: =SUMIFS(FATURAMENTO!$H$8:$H$1048576,FATURAMENTO!$K$8:$K$1048576,FUNDOS!$C7,FATURAMENTO!$S$8:$S$1048576,$O$6) -> 0
C8: CAPITAL ANNEX | D8: =SUMIFS(FATURAMENTO!$H$8:$H$1048576,FATURAMENTO!$M$8:$M$1048576,FUNDOS!$D$6,FATURAMENTO!$K$8:$K$1048576,FUNDOS!C8) -> 414150.34 | E8: =SUMIFS(FATURAMENTO!$H$8:$H$1048576,FATURAMENTO!$M$8:$M$1048576,$E$6,FATURAMENTO!$K$8:$K$1048576,C8) -> 4381.86 | F8: =D8+E8-L8 -> 418532.2 | H8: =SUMIFS(FATURAMENTO!$H$8:$H$1048576,FATURAMENTO!$M$8:$M$1048576,$H$6,FATURAMENTO!$K$8:$K$1048576,C8) -> 247856.98 | J8: =SUMIFS(FATURAMENTO!$H$8:$H$1048576,FATURAMENTO!$K$8:$K$1048576,FUNDOS!$C8,FATURAMENTO!$Q$8:$Q$1048576,FUNDOS!$J$6) -> 0 | K8: =SUMIFS(FATURAMENTO!$H$8:$H$1048576,FATURAMENTO!$K$8:$K$1048576,FUNDOS!$C8,FATURAMENTO!$Q$8:$Q$1048576,$K$6) -> 0 | L8: =J8 -> 0 | N8: =SUMIFS(FATURAMENTO!$H$8:$H$1048576,FATURAMENTO!$K$8:$K$1048576,FUNDOS!$C8,FATURAMENTO!$S$8:$S$1048576,FUNDOS!$N$6) -> 0 | O8: =SUMIFS(FATURAMENTO!$H$8:$H$1048576,FATURAMENTO!$K$8:$K$1048576,FUNDOS!$C8,FATURAMENTO!$S$8:$S$1048576,$O$6) -> 0
C9: CONTINENTAL | D9: =SUMIFS(FATURAMENTO!$H$8:$H$1048576,FATURAMENTO!$M$8:$M$1048576,FUNDOS!$D$6,FATURAMENTO!$K$8:$K$1048576,FUNDOS!C9) -> 0 | E9: =SUMIFS(FATURAMENTO!$H$8:$H$1048576,FATURAMENTO!$M$8:$M$1048576,$E$6,FATURAMENTO!$K$8:$K$1048576,C9) -> 0 | F9: =D9+E9-L9 -> 0 | H9: =SUMIFS(FATURAMENTO!$H$8:$H$1048576,FATURAMENTO!$M$8:$M$1048576,$H$6,FATURAMENTO!$K$8:$K$1048576,C9) -> 0 | J9: =SUMIFS(FATURAMENTO!$H$8:$H$1048576,FATURAMENTO!$K$8:$K$1048576,FUNDOS!$C9,FATURAMENTO!$Q$8:$Q$1048576,FUNDOS!$J$6) -> 0 | K9: =SUMIFS(FATURAMENTO!$H$8:$H$1048576,FATURAMENTO!$K$8:$K$1048576,FUNDOS!$C9,FATURAMENTO!$Q$8:$Q$1048576,$K$6) -> 0 | L9: =J9 -> 0 | N9: =SUMIFS(FATURAMENTO!$H$8:$H$1048576,FATURAMENTO!$K$8:$K$1048576,FUNDOS!$C9,FATURAMENTO!$S$8:$S$1048576,FUNDOS!$N$6) -> 0 | O9: =SUMIFS(FATURAMENTO!$H$8:$H$1048576,FATURAMENTO!$K$8:$K$1048576,FUNDOS!$C9,FATURAMENTO!$S$8:$S$1048576,$O$6) -> 0
C10: DEL MONTE | D10: =SUMIFS(FATURAMENTO!$H$8:$H$1048576,FATURAMENTO!$M$8:$M$1048576,FUNDOS!$D$6,FATURAMENTO!$K$8:$K$1048576,FUNDOS!C10) -> 4364.1 | E10: =SUMIFS(FATURAMENTO!$H$8:$H$1048576,FATURAMENTO!$M$8:$M$1048576,$E$6,FATURAMENTO!$K$8:$K$1048576,C10) -> 27611 | F10: =D10+E10-L10 -> 31975.1 | H10: =SUMIFS(FATURAMENTO!$H$8:$H$1048576,FATURAMENTO!$M$8:$M$1048576,$H$6,FATURAMENTO!$K$8:$K$1048576,C10) -> 589422.07 | J10: =SUMIFS(FATURAMENTO!$H$8:$H$1048576,FATURAMENTO!$K$8:$K$1048576,FUNDOS!$C10,FATURAMENTO!$Q$8:$Q$1048576,FUNDOS!$J$6) -> 0 | K10: =SUMIFS(FATURAMENTO!$H$8:$H$1048576,FATURAMENTO!$K$8:$K$1048576,FUNDOS!$C10,FATURAMENTO!$Q$8:$Q$1048576,$K$6) -> 0 | L10: =J10 -> 0 | N10: =SUMIFS(FATURAMENTO!$H$8:$H$1048576,FATURAMENTO!$K$8:$K$1048576,FUNDOS!$C10,FATURAMENTO!$S$8:$S$1048576,FUNDOS!$N$6) -> 36494 | O10: =SUMIFS(FATURAMENTO!$H$8:$H$1048576,FATURAMENTO!$K$8:$K$1048576,FUNDOS!$C10,FATURAMENTO!$S$8:$S$1048576,$O$6) -> 0
C11: FAMA | D11: =SUMIFS(FATURAMENTO!$H$8:$H$1048576,FATURAMENTO!$M$8:$M$1048576,FUNDOS!$D$6,FATURAMENTO!$K$8:$K$1048576,FUNDOS!C11) -> 790342.53 | E11: =SUMIFS(FATURAMENTO!$H$8:$H$1048576,FATURAMENTO!$M$8:$M$1048576,$E$6,FATURAMENTO!$K$8:$K$1048576,C11) -> 0 | F11: =D11+E11-L11 -> 790342.53 | H11: =SUMIFS(FATURAMENTO!$H$8:$H$1048576,FATURAMENTO!$M$8:$M$1048576,$H$6,FATURAMENTO!$K$8:$K$1048576,C11) -> 1387214.4 | J11: =SUMIFS(FATURAMENTO!$H$8:$H$1048576,FATURAMENTO!$K$8:$K$1048576,FUNDOS!$C11,FATURAMENTO!$Q$8:$Q$1048576,FUNDOS!$J$6) -> 0 | K11: =SUMIFS(FATURAMENTO!$H$8:$H$1048576,FATURAMENTO!$K$8:$K$1048576,FUNDOS!$C11,FATURAMENTO!$Q$8:$Q$1048576,$K$6) -> 0 | L11: =J11 -> 0 | N11: =SUMIFS(FATURAMENTO!$H$8:$H$1048576,FATURAMENTO!$K$8:$K$1048576,FUNDOS!$C11,FATURAMENTO!$S$8:$S$1048576,FUNDOS!$N$6) -> 38628.76 | O11: =SUMIFS(FATURAMENTO!$H$8:$H$1048576,FATURAMENTO!$K$8:$K$1048576,FUNDOS!$C11,FATURAMENTO!$S$8:$S$1048576,$O$6) -> 0
C12: H8 | D12: =SUMIFS(FATURAMENTO!$H$8:$H$1048576,FATURAMENTO!$M$8:$M$1048576,FUNDOS!$D$6,FATURAMENTO!$K$8:$K$1048576,FUNDOS!C12) -> 404006.17 | E12: =SUMIFS(FATURAMENTO!$H$8:$H$1048576,FATURAMENTO!$M$8:$M$1048576,$E$6,FATURAMENTO!$K$8:$K$1048576,C12) -> 35045.41 | F12: =D12+E12-L12 -> 439051.58 | H12: =SUMIFS(FATURAMENTO!$H$8:$H$1048576,FATURAMENTO!$M$8:$M$1048576,$H$6,FATURAMENTO!$K$8:$K$1048576,C12) -> 380480.24 | J12: =SUMIFS(FATURAMENTO!$H$8:$H$1048576,FATURAMENTO!$K$8:$K$1048576,FUNDOS!$C12,FATURAMENTO!$Q$8:$Q$1048576,FUNDOS!$J$6) -> 0 | K12: =SUMIFS(FATURAMENTO!$H$8:$H$1048576,FATURAMENTO!$K$8:$K$1048576,FUNDOS!$C12,FATURAMENTO!$Q$8:$Q$1048576,$K$6) -> 0 | L12: =J12 -> 0 | N12: =SUMIFS(FATURAMENTO!$H$8:$H$1048576,FATURAMENTO!$K$8:$K$1048576,FUNDOS!$C12,FATURAMENTO!$S$8:$S$1048576,FUNDOS!$N$6) -> 17192 | O12: =SUMIFS(FATURAMENTO!$H$8:$H$1048576,FATURAMENTO!$K$8:$K$1048576,FUNDOS!$C12,FATURAMENTO!$S$8:$S$1048576,$O$6) -> 0
C13: KHAVA | D13: =SUMIFS(FATURAMENTO!$H$8:$H$1048576,FATURAMENTO!$M$8:$M$1048576,FUNDOS!$D$6,FATURAMENTO!$K$8:$K$1048576,FUNDOS!C13) -> 0 | E13: =SUMIFS(FATURAMENTO!$H$8:$H$1048576,FATURAMENTO!$M$8:$M$1048576,$E$6,FATURAMENTO!$K$8:$K$1048576,C13) -> 0 | F13: =D13+E13-L13 -> 0 | H13: =SUMIFS(FATURAMENTO!$H$8:$H$1048576,FATURAMENTO!$M$8:$M$1048576,$H$6,FATURAMENTO!$K$8:$K$1048576,C13) -> 0 | J13: =SUMIFS(FATURAMENTO!$H$8:$H$1048576,FATURAMENTO!$K$8:$K$1048576,FUNDOS!$C13,FATURAMENTO!$Q$8:$Q$1048576,FUNDOS!$J$6) -> 0 | K13: =SUMIFS(FATURAMENTO!$H$8:$H$1048576,FATURAMENTO!$K$8:$K$1048576,FUNDOS!$C13,FATURAMENTO!$Q$8:$Q$1048576,$K$6) -> 0 | L13: =J13 -> 0 | N13: =SUMIFS(FATURAMENTO!$H$8:$H$1048576,FATURAMENTO!$K$8:$K$1048576,FUNDOS!$C13,FATURAMENTO!$S$8:$S$1048576,FUNDOS!$N$6) -> 0 | O13: =SUMIFS(FATURAMENTO!$H$8:$H$1048576,FATURAMENTO!$K$8:$K$1048576,FUNDOS!$C13,FATURAMENTO!$S$8:$S$1048576,$O$6) -> 0
C14: LEPTA | D14: =SUMIFS(FATURAMENTO!$H$8:$H$1048576,FATURAMENTO!$M$8:$M$1048576,FUNDOS!$D$6,FATURAMENTO!$K$8:$K$1048576,FUNDOS!C14) -> 125131.28 | E14: =SUMIFS(FATURAMENTO!$H$8:$H$1048576,FATURAMENTO!$M$8:$M$1048576,$E$6,FATURAMENTO!$K$8:$K$1048576,C14) -> 0 | F14: =D14+E14-L14 -> 125131.28 | H14: =SUMIFS(FATURAMENTO!$H$8:$H$1048576,FATURAMENTO!$M$8:$M$1048576,$H$6,FATURAMENTO!$K$8:$K$1048576,C14) -> 345775 | J14: =SUMIFS(FATURAMENTO!$H$8:$H$1048576,FATURAMENTO!$K$8:$K$1048576,FUNDOS!$C14,FATURAMENTO!$Q$8:$Q$1048576,FUNDOS!$J$6) -> 0 | K14: =SUMIFS(FATURAMENTO!$H$8:$H$1048576,FATURAMENTO!$K$8:$K$1048576,FUNDOS!$C14,FATURAMENTO!$Q$8:$Q$1048576,$K$6) -> 0 | L14: =J14 -> 0 | N14: =SUMIFS(FATURAMENTO!$H$8:$H$1048576,FATURAMENTO!$K$8:$K$1048576,FUNDOS!$C14,FATURAMENTO!$S$8:$S$1048576,FUNDOS!$N$6) -> 0 | O14: =SUMIFS(FATURAMENTO!$H$8:$H$1048576,FATURAMENTO!$K$8:$K$1048576,FUNDOS!$C14,FATURAMENTO!$S$8:$S$1048576,$O$6) -> 0
C15: ONIX | D15: =SUMIFS(FATURAMENTO!$H$8:$H$1048576,FATURAMENTO!$M$8:$M$1048576,FUNDOS!$D$6,FATURAMENTO!$K$8:$K$1048576,FUNDOS!C15) -> 248763.27 | E15: =SUMIFS(FATURAMENTO!$H$8:$H$1048576,FATURAMENTO!$M$8:$M$1048576,$E$6,FATURAMENTO!$K$8:$K$1048576,C15) -> 0 | F15: =D15+E15-L15 -> 248763.27 | H15: =SUMIFS(FATURAMENTO!$H$8:$H$1048576,FATURAMENTO!$M$8:$M$1048576,$H$6,FATURAMENTO!$K$8:$K$1048576,C15) -> 26137.19 | J15: =SUMIFS(FATURAMENTO!$H$8:$H$1048576,FATURAMENTO!$K$8:$K$1048576,FUNDOS!$C15,FATURAMENTO!$Q$8:$Q$1048576,FUNDOS!$J$6) -> 0 | K15: =SUMIFS(FATURAMENTO!$H$8:$H$1048576,FATURAMENTO!$K$8:$K$1048576,FUNDOS!$C15,FATURAMENTO!$Q$8:$Q$1048576,$K$6) -> 0 | L15: =J15 -> 0 | N15: =SUMIFS(FATURAMENTO!$H$8:$H$1048576,FATURAMENTO!$K$8:$K$1048576,FUNDOS!$C15,FATURAMENTO!$S$8:$S$1048576,FUNDOS!$N$6) -> 0 | O15: =SUMIFS(FATURAMENTO!$H$8:$H$1048576,FATURAMENTO!$K$8:$K$1048576,FUNDOS!$C15,FATURAMENTO!$S$8:$S$1048576,$O$6) -> 0
C16: VALE RIO CLARO | D16: =SUMIFS(FATURAMENTO!$H$8:$H$1048576,FATURAMENTO!$M$8:$M$1048576,FUNDOS!$D$6,FATURAMENTO!$K$8:$K$1048576,FUNDOS!C16) -> 33557.59 | E16: =SUMIFS(FATURAMENTO!$H$8:$H$1048576,FATURAMENTO!$M$8:$M$1048576,$E$6,FATURAMENTO!$K$8:$K$1048576,C16) -> 22669.17 | F16: =D16+E16-L16 -> 54893.43 | H16: =SUMIFS(FATURAMENTO!$H$8:$H$1048576,FATURAMENTO!$M$8:$M$1048576,$H$6,FATURAMENTO!$K$8:$K$1048576,C16) -> 361255.92 | J16: =SUMIFS(FATURAMENTO!$H$8:$H$1048576,FATURAMENTO!$K$8:$K$1048576,FUNDOS!$C16,FATURAMENTO!$Q$8:$Q$1048576,FUNDOS!$J$6) -> 1333.33 | K16: =SUMIFS(FATURAMENTO!$H$8:$H$1048576,FATURAMENTO!$K$8:$K$1048576,FUNDOS!$C16,FATURAMENTO!$Q$8:$Q$1048576,$K$6) -> 4540 | L16: =J16 -> 1333.33 | N16: =SUMIFS(FATURAMENTO!$H$8:$H$1048576,FATURAMENTO!$K$8:$K$1048576,FUNDOS!$C16,FATURAMENTO!$S$8:$S$1048576,FUNDOS!$N$6) -> 0 | O16: =SUMIFS(FATURAMENTO!$H$8:$H$1048576,FATURAMENTO!$K$8:$K$1048576,FUNDOS!$C16,FATURAMENTO!$S$8:$S$1048576,$O$6) -> 1333.33
C17: IGNIS | D17: =SUMIFS(FATURAMENTO!$H$8:$H$1048576,FATURAMENTO!$M$8:$M$1048576,FUNDOS!$D$6,FATURAMENTO!$K$8:$K$1048576,FUNDOS!C17) -> 410814.8 | E17: =SUMIFS(FATURAMENTO!$H$8:$H$1048576,FATURAMENTO!$M$8:$M$1048576,$E$6,FATURAMENTO!$K$8:$K$1048576,C17) -> 15986.08 | F17: =D17+E17-L17 -> 426800.88 | H17: =SUMIFS(FATURAMENTO!$H$8:$H$1048576,FATURAMENTO!$M$8:$M$1048576,$H$6,FATURAMENTO!$K$8:$K$1048576,C17) -> 80807.24 | J17: =SUMIFS(FATURAMENTO!$H$8:$H$1048576,FATURAMENTO!$K$8:$K$1048576,FUNDOS!$C17,FATURAMENTO!$Q$8:$Q$1048576,FUNDOS!$J$6) -> 0 | K17: =SUMIFS(FATURAMENTO!$H$8:$H$1048576,FATURAMENTO!$K$8:$K$1048576,FUNDOS!$C17,FATURAMENTO!$Q$8:$Q$1048576,$K$6) -> 7894.96 | L17: =J17 -> 0 | N17: =SUMIFS(FATURAMENTO!$H$8:$H$1048576,FATURAMENTO!$K$8:$K$1048576,FUNDOS!$C17,FATURAMENTO!$S$8:$S$1048576,FUNDOS!$N$6) -> 0 | O17: =SUMIFS(FATURAMENTO!$H$8:$H$1048576,FATURAMENTO!$K$8:$K$1048576,FUNDOS!$C17,FATURAMENTO!$S$8:$S$1048576,$O$6) -> 0
F20: =D20+E20 -> 0 | H20: =SUMIFS(FATURAMENTO!$H$8:$H$1048576,FATURAMENTO!$M$8:$M$1048576,$H$6,FATURAMENTO!$K$8:$K$1048576,C20) -> 0 | L20: =SUMIFS(FATURAMENTO!$H$8:$H$1048576,FATURAMENTO!$Q$8:$Q$1048576,FUNDOS!$L$6,FATURAMENTO!$K$8:$K$1048576,FUNDOS!$C20) -> 0
F21: =D21+E21 -> 0 | H21: =SUMIFS(FATURAMENTO!$H$8:$H$1048576,FATURAMENTO!$M$8:$M$1048576,$H$6,FATURAMENTO!$K$8:$K$1048576,C21) -> 0 | L21: =SUMIFS(FATURAMENTO!$H$8:$H$1048576,FATURAMENTO!$Q$8:$Q$1048576,FUNDOS!$L$6,FATURAMENTO!$K$8:$K$1048576,FUNDOS!$C21) -> 0
D22: =SUM(D7:D16) -> 2170829.3 | E22: =SUM(E7:E16) -> 89707.44 | F22: =SUM(F7:F16) -> 2259203.4 | H22: =SUM(H7:H16) -> 3405359 | J22: =SUM(J7:J21) -> 1333.33 | K22: =SUM(K7:K21) -> 12434.96 | L22: =SUM(L7:L21) -> 1333.33 | N22: =SUM(N7:N21) -> 92314.76 | O22: =SUM(O7:O21) -> 1333.33

Sheet PM
A5: SIMULACAO PRAZO MEDIO
D6: PRAZO MEDIO + | E6: =AVERAGE(Tabela46[PRAZO D+X]) -> 46.857143
A7: DT OPERACAO | B7: 46094 | D7: D + | E7: 3 | H7: CALCULO PM
D8: PM PONDERADO | E8: =IF(ISERROR(SUM(E13:E352)/SUM(B13:B351))=TRUE,0,(SUM(E13:E352)/SUM(B13:B351))) -> 49.968189 | H8: 52.635361
A10: TOTAL BRUTO | B10: =SUM(Tabela46[VALOR]) -> 62369 | D10: QTD. TITULO | E10: =COUNT(B13:B90) -> 21 | H10: SIMULACAO TAXA ACORDADA | K10: TAXA ACORDADA
A12: DT VENCIMENTO | B12: VALOR | C12: PRAZO NOMINAL | D12: PRAZO D+X | E12: PR X VALOR | H12: INSTITUIÇÃO | I12: VALE RIO CLARO | K12: CÓDIGO | L12: INSTITUICAO | M12: TIPO OPERACAO | N12: TIPO INSTITUICAO | O12: TAXA ACORDADA | P12: TAR DE COB | Q12: REEMB TED / TRANSF | R12: ANALISE E CONTRATO | S12: REEMB ASSINAT DIG | T12: REEMB SERASA | U12: TAC
A13: 46121 | B13: 1878 | C13: =IF(A13="","",A13-$B$7) -> 27 | D13: =IF(A13="","",IF($B$7="","",IF(OR(WEEKDAY(A13)=5,WEEKDAY(A13)=6,WEEKDAY(A13)=7),A13-$B$7+$E$7+2,IF(WEEKDAY(A13)=1,A13-$B$7+$E$7+1,A13-$B$7+$E$7)))) -> 32 | E13: =IF(D13="","",IF(B13="","",IF(A13="","",IF($B$7="","",(D13*B13))))) -> 60096 | H13: TIPO OPERAÇÃO | I13: BOLETO | K13: =IFERROR(CONCATENATE(Tabela3[[#This Row],[INSTITUICAO]]," ",Tabela3[[#This Row],[TIPO OPERACAO]]," ",Tabela3[[#This Row],[TIPO INSTITUICAO]])," ") -> OLAM BOLETO FIDC | L13: OLAM | M13: BOLETO | N13: FIDC | O13: 0.023
A14: 46128 | B14: 1368 | C14: =IF(A14="","",A14-$B$7) -> 34 | D14: =IF(A14="","",IF($B$7="","",IF(OR(WEEKDAY(A14)=5,WEEKDAY(A14)=6,WEEKDAY(A14)=7),A14-$B$7+$E$7+2,IF(WEEKDAY(A14)=1,A14-$B$7+$E$7+1,A14-$B$7+$E$7)))) -> 39 | E14: =IF(D14="","",IF(B14="","",IF(A14="","",IF($B$7="","",(D14*B14))))) -> 53352 | H14: TIPO INSTITUICAO | I14: FIDC | K14: =IFERROR(CONCATENATE(Tabela3[[#This Row],[INSTITUICAO]]," ",Tabela3[[#This Row],[TIPO OPERACAO]]," ",Tabela3[[#This Row],[TIPO INSTITUICAO]])," ") -> RDF BOLETO FIDC | L14: RDF | M14: BOLETO | N14: FIDC | O14: 0.0175
A15: 46135 | B15: 1368 | C15: =IF(A15="","",A15-$B$7) -> 41 | D15: =IF(A15="","",IF($B$7="","",IF(OR(WEEKDAY(A15)=5,WEEKDAY(A15)=6,WEEKDAY(A15)=7),A15-$B$7+$E$7+2,IF(WEEKDAY(A15)=1,A15-$B$7+$E$7+1,A15-$B$7+$E$7)))) -> 46 | E15: =IF(D15="","",IF(B15="","",IF(A15="","",IF($B$7="","",(D15*B15))))) -> 62928 | H15: TAXA ACORDADA | I15: 0.0403 | K15: =IFERROR(CONCATENATE(Tabela3[[#This Row],[INSTITUICAO]]," ",Tabela3[[#This Row],[TIPO OPERACAO]]," ",Tabela3[[#This Row],[TIPO INSTITUICAO]])," ") -> ACREDITAR BOLETO FIDC | L15: ACREDITAR | M15: BOLETO | N15: FIDC | O15: 0.025
A16: 46142 | B16: 1368 | C16: =IF(A16="","",A16-$B$7) -> 48 | D16: =IF(A16="","",IF($B$7="","",IF(OR(WEEKDAY(A16)=5,WEEKDAY(A16)=6,WEEKDAY(A16)=7),A16-$B$7+$E$7+2,IF(WEEKDAY(A16)=1,A16-$B$7+$E$7+1,A16-$B$7+$E$7)))) -> 53 | E16: =IF(D16="","",IF(B16="","",IF(A16="","",IF($B$7="","",(D16*B16))))) -> 72504 | H16: PRAZO MEDIO | I16: =E8 -> 49.968189 | K16: =IFERROR(CONCATENATE(Tabela3[[#This Row],[INSTITUICAO]]," ",Tabela3[[#This Row],[TIPO OPERACAO]]," ",Tabela3[[#This Row],[TIPO INSTITUICAO]])," ") -> KREDITARE BOLETO FIDC | L16: KREDITARE | M16: BOLETO | N16: FIDC | O16: 0.022
A17: 46121 | B17: 1368 | C17: =IF(A17="","",A17-$B$7) -> 27 | D17: =IF(A17="","",IF($B$7="","",IF(OR(WEEKDAY(A17)=5,WEEKDAY(A17)=6,WEEKDAY(A17)=7),A17-$B$7+$E$7+2,IF(WEEKDAY(A17)=1,A17-$B$7+$E$7+1,A17-$B$7+$E$7)))) -> 32 | E17: =IF(D17="","",IF(B17="","",IF(A17="","",IF($B$7="","",(D17*B17))))) -> 43776 | H17: VALOR BRUTO | I17: =B10 -> 62369 | K17: =IFERROR(CONCATENATE(Tabela3[[#This Row],[INSTITUICAO]]," ",Tabela3[[#This Row],[TIPO OPERACAO]]," ",Tabela3[[#This Row],[TIPO INSTITUICAO]])," ") -> ASIA BOLETO FIDC | L17: ASIA | M17: BOLETO | N17: FIDC | O17: 0.018
A18: 46128 | B18: 1368 | C18: =IF(A18="","",A18-$B$7) -> 34 | D18: =IF(A18="","",IF($B$7="","",IF(OR(WEEKDAY(A18)=5,WEEKDAY(A18)=6,WEEKDAY(A18)=7),A18-$B$7+$E$7+2,IF(WEEKDAY(A18)=1,A18-$B$7+$E$7+1,A18-$B$7+$E$7)))) -> 39 | E18: =IF(D18="","",IF(B18="","",IF(A18="","",IF($B$7="","",(D18*B18))))) -> 53352 | H18: VALOR LIQUIDO | I18: 44675.69 | K18: =IFERROR(CONCATENATE(Tabela3[[#This Row],[INSTITUICAO]]," ",Tabela3[[#This Row],[TIPO OPERACAO]]," ",Tabela3[[#This Row],[TIPO INSTITUICAO]])," ") -> MOKA FOMENTO FIDC | L18: MOKA | M18: FOMENTO | N18: FIDC | O18: 0.031
A19: 46135 | B19: 1368 | C19: =IF(A19="","",A19-$B$7) -> 41 | D19: =IF(A19="","",IF($B$7="","",IF(OR(WEEKDAY(A19)=5,WEEKDAY(A19)=6,WEEKDAY(A19)=7),A19-$B$7+$E$7+2,IF(WEEKDAY(A19)=1,A19-$B$7+$E$7+1,A19-$B$7+$E$7)))) -> 46 | E19: =IF(D19="","",IF(B19="","",IF(A19="","",IF($B$7="","",(D19*B19))))) -> 62928 | H19: JUROS | I19: =I17-I18 -> 17693.31 | K19: =IFERROR(CONCATENATE(Tabela3[[#This Row],[INSTITUICAO]]," ",Tabela3[[#This Row],[TIPO OPERACAO]]," ",Tabela3[[#This Row],[TIPO INSTITUICAO]])," ") -> KREDITARE CHEQUE FIDC | L19: KREDITARE | M19: CHEQUE | N19: FIDC | O19: 0.025
A20: 46142 | B20: 1368 | C20: =IF(A20="","",A20-$B$7) -> 48 | D20: =IF(A20="","",IF($B$7="","",IF(OR(WEEKDAY(A20)=5,WEEKDAY(A20)=6,WEEKDAY(A20)=7),A20-$B$7+$E$7+2,IF(WEEKDAY(A20)=1,A20-$B$7+$E$7+1,A20-$B$7+$E$7)))) -> 53 | E20: =IF(D20="","",IF(B20="","",IF(A20="","",IF($B$7="","",(D20*B20))))) -> 72504 | H20: MULTA | I20: 0 | K20: =IFERROR(CONCATENATE(Tabela3[[#This Row],[INSTITUICAO]]," ",Tabela3[[#This Row],[TIPO OPERACAO]]," ",Tabela3[[#This Row],[TIPO INSTITUICAO]])," ") -> VIP BOLETO FACT | L20: VIP | M20: BOLETO | N20: FACT | O20: 0.018
A21: 46127 | B21: 1108 | C21: =IF(A21="","",A21-$B$7) -> 33 | D21: =IF(A21="","",IF($B$7="","",IF(OR(WEEKDAY(A21)=5,WEEKDAY(A21)=6,WEEKDAY(A21)=7),A21-$B$7+$E$7+2,IF(WEEKDAY(A21)=1,A21-$B$7+$E$7+1,A21-$B$7+$E$7)))) -> 36 | E21: =IF(D21="","",IF(B21="","",IF(A21="","",IF($B$7="","",(D21*B21))))) -> 39888 | H21: VALOR MULTA | I21: =I20*I17 -> 0 | K21: =IFERROR(CONCATENATE(Tabela3[[#This Row],[INSTITUICAO]]," ",Tabela3[[#This Row],[TIPO OPERACAO]]," ",Tabela3[[#This Row],[TIPO INSTITUICAO]])," ") -> LANA BOLETO FIDC | L21: LANA | M21: BOLETO | N21: FIDC | O21: 0.019
A22: 46142 | B22: 1108 | C22: =IF(A22="","",A22-$B$7) -> 48 | D22: =IF(A22="","",IF($B$7="","",IF(OR(WEEKDAY(A22)=5,WEEKDAY(A22)=6,WEEKDAY(A22)=7),A22-$B$7+$E$7+2,IF(WEEKDAY(A22)=1,A22-$B$7+$E$7+1,A22-$B$7+$E$7)))) -> 53 | E22: =IF(D22="","",IF(B22="","",IF(A22="","",IF($B$7="","",(D22*B22))))) -> 58724 | H22: TOTAL | I22: =SUM(I19:I20) -> 17693.31 | K22: =IFERROR(CONCATENATE(Tabela3[[#This Row],[INSTITUICAO]]," ",Tabela3[[#This Row],[TIPO OPERACAO]]," ",Tabela3[[#This Row],[TIPO INSTITUICAO]])," ") -> IOSAN BOLETO FIDC | L22: IOSAN | M22: BOLETO | N22: FIDC | O22: 0.023
A23: 46157 | B23: 9972 | C23: =IF(A23="","",A23-$B$7) -> 63 | D23: =IF(A23="","",IF($B$7="","",IF(OR(WEEKDAY(A23)=5,WEEKDAY(A23)=6,WEEKDAY(A23)=7),A23-$B$7+$E$7+2,IF(WEEKDAY(A23)=1,A23-$B$7+$E$7+1,A23-$B$7+$E$7)))) -> 68 | E23: =IF(D23="","",IF(B23="","",IF(A23="","",IF($B$7="","",(D23*B23))))) -> 678096 | K23: =IFERROR(CONCATENATE(Tabela3[[#This Row],[INSTITUICAO]]," ",Tabela3[[#This Row],[TIPO OPERACAO]]," ",Tabela3[[#This Row],[TIPO INSTITUICAO]])," ") -> ACTIVA BOLETO FIDC | L23: ACTIVA | M23: BOLETO | N23: FIDC | O23: 0.023
A24: 46127 | B24: 9972 | C24: =IF(A24="","",A24-$B$7) -> 33 | D24: =IF(A24="","",IF($B$7="","",IF(OR(WEEKDAY(A24)=5,WEEKDAY(A24)=6,WEEKDAY(A24)=7),A24-$B$7+$E$7+2,IF(WEEKDAY(A24)=1,A24-$B$7+$E$7+1,A24-$B$7+$E$7)))) -> 36 | E24: =IF(D24="","",IF(B24="","",IF(A24="","",IF($B$7="","",(D24*B24))))) -> 358992 | H24: LIQ. OPERAÇÃO | I24: 0 | K24: =IFERROR(CONCATENATE(Tabela3[[#This Row],[INSTITUICAO]]," ",Tabela3[[#This Row],[TIPO OPERACAO]]," ",Tabela3[[#This Row],[TIPO INSTITUICAO]])," ") -> GENEBRA BOLETO FIDC | L24: GENEBRA | M24: BOLETO | N24: FIDC
A25: 46142 | B25: 9972 | C25: =IF(A25="","",A25-$B$7) -> 48 | D25: =IF(A25="","",IF($B$7="","",IF(OR(WEEKDAY(A25)=5,WEEKDAY(A25)=6,WEEKDAY(A25)=7),A25-$B$7+$E$7+2,IF(WEEKDAY(A25)=1,A25-$B$7+$E$7+1,A25-$B$7+$E$7)))) -> 53 | E25: =IF(D25="","",IF(B25="","",IF(A25="","",IF($B$7="","",(D25*B25))))) -> 528516 | H25: TOTAL DEDUÇÕES | I25: =I17-I24 -> 62369 | K25: =IFERROR(CONCATENATE(Tabela3[[#This Row],[INSTITUICAO]]," ",Tabela3[[#This Row],[TIPO OPERACAO]]," ",Tabela3[[#This Row],[TIPO INSTITUICAO]])," ") -> DEL MONTE BOLETO FIDC | L25: DEL MONTE | M25: BOLETO | N25: FIDC | O25: 0.021
A26: 46157 | B26: 3413 | C26: =IF(A26="","",A26-$B$7) -> 63 | D26: =IF(A26="","",IF($B$7="","",IF(OR(WEEKDAY(A26)=5,WEEKDAY(A26)=6,WEEKDAY(A26)=7),A26-$B$7+$E$7+2,IF(WEEKDAY(A26)=1,A26-$B$7+$E$7+1,A26-$B$7+$E$7)))) -> 68 | E26: =IF(D26="","",IF(B26="","",IF(A26="","",IF($B$7="","",(D26*B26))))) -> 232084 | H26: TAXA COBRADA | I26: =I25/I17/I16*30 -> 0.60038197 | K26: =IFERROR(CONCATENATE(Tabela3[[#This Row],[INSTITUICAO]]," ",Tabela3[[#This Row],[TIPO OPERACAO]]," ",Tabela3[[#This Row],[TIPO INSTITUICAO]])," ") -> DEL MONTE COMISSARIA FIDC | L26: DEL MONTE | M26: COMISSARIA | N26: FIDC | O26: 0.028
A27: 46126 | B27: 2377 | C27: =IF(A27="","",A27-$B$7) -> 32 | D27: =IF(A27="","",IF($B$7="","",IF(OR(WEEKDAY(A27)=5,WEEKDAY(A27)=6,WEEKDAY(A27)=7),A27-$B$7+$E$7+2,IF(WEEKDAY(A27)=1,A27-$B$7+$E$7+1,A27-$B$7+$E$7)))) -> 35 | E27: =IF(D27="","",IF(B27="","",IF(A27="","",IF($B$7="","",(D27*B27))))) -> 83195 | H27: DIFERENCA | I27: =I18-(I17-I25) -> 44675.69 | K27: =IFERROR(CONCATENATE(Tabela3[[#This Row],[INSTITUICAO]]," ",Tabela3[[#This Row],[TIPO OPERACAO]]," ",Tabela3[[#This Row],[TIPO INSTITUICAO]])," ") -> SQUARE BOLETO FIDC | L27: SQUARE | M27: BOLETO | N27: FIDC | O27: 0.0255
A28: 46140 | B28: 2377 | C28: =IF(A28="","",A28-$B$7) -> 46 | D28: =IF(A28="","",IF($B$7="","",IF(OR(WEEKDAY(A28)=5,WEEKDAY(A28)=6,WEEKDAY(A28)=7),A28-$B$7+$E$7+2,IF(WEEKDAY(A28)=1,A28-$B$7+$E$7+1,A28-$B$7+$E$7)))) -> 49 | E28: =IF(D28="","",IF(B28="","",IF(A28="","",IF($B$7="","",(D28*B28))))) -> 116473 | H28: DIFERENCA % | I28: =I26-I15 -> 0.56008197 | K28: =IFERROR(CONCATENATE(Tabela3[[#This Row],[INSTITUICAO]]," ",Tabela3[[#This Row],[TIPO OPERACAO]]," ",Tabela3[[#This Row],[TIPO INSTITUICAO]])," ") -> SOMA BOLETO FIDC | L28: SOMA | M28: BOLETO | N28: FIDC | O28: 0.018
A29: 46154 | B29: 2377 | C29: =IF(A29="","",A29-$B$7) -> 60 | D29: =IF(A29="","",IF($B$7="","",IF(OR(WEEKDAY(A29)=5,WEEKDAY(A29)=6,WEEKDAY(A29)=7),A29-$B$7+$E$7+2,IF(WEEKDAY(A29)=1,A29-$B$7+$E$7+1,A29-$B$7+$E$7)))) -> 63 | E29: =IF(D29="","",IF(B29="","",IF(A29="","",IF($B$7="","",(D29*B29))))) -> 149751 | K29: =IFERROR(CONCATENATE(Tabela3[[#This Row],[INSTITUICAO]]," ",Tabela3[[#This Row],[TIPO OPERACAO]]," ",Tabela3[[#This Row],[TIPO INSTITUICAO]])," ") -> SOMA CHEQUE FIDC | L29: SOMA | M29: CHEQUE | N29: FIDC | O29: 0.018
A30: 46126 | B30: 2377 | C30: =IF(A30="","",A30-$B$7) -> 32 | D30: =IF(A30="","",IF($B$7="","",IF(OR(WEEKDAY(A30)=5,WEEKDAY(A30)=6,WEEKDAY(A30)=7),A30-$B$7+$E$7+2,IF(WEEKDAY(A30)=1,A30-$B$7+$E$7+1,A30-$B$7+$E$7)))) -> 35 | E30: =IF(D30="","",IF(B30="","",IF(A30="","",IF($B$7="","",(D30*B30))))) -> 83195 | K30: =IFERROR(CONCATENATE(Tabela3[[#This Row],[INSTITUICAO]]," ",Tabela3[[#This Row],[TIPO OPERACAO]]," ",Tabela3[[#This Row],[TIPO INSTITUICAO]])," ") -> VALINVEST FOMENTO SEC | L30: VALINVEST | M30: FOMENTO | N30: SEC | O30: 0.04
A31: 46140 | B31: 2377 | C31: =IF(A31="","",A31-$B$7) -> 46 | D31: =IF(A31="","",IF($B$7="","",IF(OR(WEEKDAY(A31)=5,WEEKDAY(A31)=6,WEEKDAY(A31)=7),A31-$B$7+$E$7+2,IF(WEEKDAY(A31)=1,A31-$B$7+$E$7+1,A31-$B$7+$E$7)))) -> 49 | E31: =IF(D31="","",IF(B31="","",IF(A31="","",IF($B$7="","",(D31*B31))))) -> 116473 | K31: =IFERROR(CONCATENATE(Tabela3[[#This Row],[INSTITUICAO]]," ",Tabela3[[#This Row],[TIPO OPERACAO]]," ",Tabela3[[#This Row],[TIPO INSTITUICAO]])," ") -> VALINVEST CHEQUE SEC | L31: VALINVEST | M31: CHEQUE | N31: SEC | O31: 0.032
A32: 46154 | B32: 2377 | C32: =IF(A32="","",A32-$B$7) -> 60 | D32: =IF(A32="","",IF($B$7="","",IF(OR(WEEKDAY(A32)=5,WEEKDAY(A32)=6,WEEKDAY(A32)=7),A32-$B$7+$E$7+2,IF(WEEKDAY(A32)=1,A32-$B$7+$E$7+1,A32-$B$7+$E$7)))) -> 63 | E32: =IF(D32="","",IF(B32="","",IF(A32="","",IF($B$7="","",(D32*B32))))) -> 149751 | K32: =IFERROR(CONCATENATE(Tabela3[[#This Row],[INSTITUICAO]]," ",Tabela3[[#This Row],[TIPO OPERACAO]]," ",Tabela3[[#This Row],[TIPO INSTITUICAO]])," ") -> ANTARES CHEQUE SEC | L32: ANTARES | M32: CHEQUE | N32: SEC | O32: 0.027
A33: 46127 | B33: 1108 | C33: =IF(A33="","",A33-$B$7) -> 33 | D33: =IF(A33="","",IF($B$7="","",IF(OR(WEEKDAY(A33)=5,WEEKDAY(A33)=6,WEEKDAY(A33)=7),A33-$B$7+$E$7+2,IF(WEEKDAY(A33)=1,A33-$B$7+$E$7+1,A33-$B$7+$E$7)))) -> 36 | E33: =IF(D33="","",IF(B33="","",IF(A33="","",IF($B$7="","",(D33*B33))))) -> 39888 | K33: =IFERROR(CONCATENATE(Tabela3[[#This Row],[INSTITUICAO]]," ",Tabela3[[#This Row],[TIPO OPERACAO]]," ",Tabela3[[#This Row],[TIPO INSTITUICAO]])," ") -> MFM CHEQUE PF | L33: MFM | M33: CHEQUE | N33: PF | O33: 0.027
C34: =IF(A34="","",A34-$B$7) | D34: =IF(A34="","",IF($B$7="","",IF(OR(WEEKDAY(A34)=5,WEEKDAY(A34)=6,WEEKDAY(A34)=7),A34-$B$7+$E$7+2,IF(WEEKDAY(A34)=1,A34-$B$7+$E$7+1,A34-$B$7+$E$7)))) | E34: =IF(D34="","",IF(B34="","",IF(A34="","",IF($B$7="","",(D34*B34))))) | K34: =IFERROR(CONCATENATE(Tabela3[[#This Row],[INSTITUICAO]]," ",Tabela3[[#This Row],[TIPO OPERACAO]]," ",Tabela3[[#This Row],[TIPO INSTITUICAO]])," ") -> DXM CHEQUE SEC | L34: DXM | M34: CHEQUE | N34: SEC | O34: 0.027
C35: =IF(A35="","",A35-$B$7) | D35: =IF(A35="","",IF($B$7="","",IF(OR(WEEKDAY(A35)=5,WEEKDAY(A35)=6,WEEKDAY(A35)=7),A35-$B$7+$E$7+2,IF(WEEKDAY(A35)=1,A35-$B$7+$E$7+1,A35-$B$7+$E$7)))) | E35: =IF(D35="","",IF(B35="","",IF(A35="","",IF($B$7="","",(D35*B35))))) | K35: =IFERROR(CONCATENATE(Tabela3[[#This Row],[INSTITUICAO]]," ",Tabela3[[#This Row],[TIPO OPERACAO]]," ",Tabela3[[#This Row],[TIPO INSTITUICAO]])," ") -> SP INVEST CHEQUE SEC | L35: SP INVEST | M35: CHEQUE | N35: SEC | O35: 0.032
C36: =IF(A36="","",A36-$B$7) | D36: =IF(A36="","",IF($B$7="","",IF(OR(WEEKDAY(A36)=5,WEEKDAY(A36)=6,WEEKDAY(A36)=7),A36-$B$7+$E$7+2,IF(WEEKDAY(A36)=1,A36-$B$7+$E$7+1,A36-$B$7+$E$7)))) | E36: =IF(D36="","",IF(B36="","",IF(A36="","",IF($B$7="","",(D36*B36))))) | K36: =IFERROR(CONCATENATE(Tabela3[[#This Row],[INSTITUICAO]]," ",Tabela3[[#This Row],[TIPO OPERACAO]]," ",Tabela3[[#This Row],[TIPO INSTITUICAO]])," ") -> INVISTA CHEQUE SEC | L36: INVISTA | M36: CHEQUE | N36: SEC | O36: 0.028
C37: =IF(A37="","",A37-$B$7) | D37: =IF(A37="","",IF($B$7="","",IF(OR(WEEKDAY(A37)=5,WEEKDAY(A37)=6,WEEKDAY(A37)=7),A37-$B$7+$E$7+2,IF(WEEKDAY(A37)=1,A37-$B$7+$E$7+1,A37-$B$7+$E$7)))) | E37: =IF(D37="","",IF(B37="","",IF(A37="","",IF($B$7="","",(D37*B37))))) | K37: =IFERROR(CONCATENATE(Tabela3[[#This Row],[INSTITUICAO]]," ",Tabela3[[#This Row],[TIPO OPERACAO]]," ",Tabela3[[#This Row],[TIPO INSTITUICAO]])," ") -> MATURITY CHEQUE SEC | L37: MATURITY | M37: CHEQUE | N37: SEC | O37: 0.03
C38: =IF(A38="","",A38-$B$7) | D38: =IF(A38="","",IF($B$7="","",IF(OR(WEEKDAY(A38)=5,WEEKDAY(A38)=6,WEEKDAY(A38)=7),A38-$B$7+$E$7+2,IF(WEEKDAY(A38)=1,A38-$B$7+$E$7+1,A38-$B$7+$E$7)))) | E38: =IF(D38="","",IF(B38="","",IF(A38="","",IF($B$7="","",(D38*B38))))) | K38: =IFERROR(CONCATENATE(Tabela3[[#This Row],[INSTITUICAO]]," ",Tabela3[[#This Row],[TIPO OPERACAO]]," ",Tabela3[[#This Row],[TIPO INSTITUICAO]])," ") -> BANICRED CHEQUE FIDC | L38: BANICRED | M38: CHEQUE | N38: FIDC | O38: 0.018
C39: =IF(A39="","",A39-$B$7) | D39: =IF(A39="","",IF($B$7="","",IF(OR(WEEKDAY(A39)=5,WEEKDAY(A39)=6,WEEKDAY(A39)=7),A39-$B$7+$E$7+2,IF(WEEKDAY(A39)=1,A39-$B$7+$E$7+1,A39-$B$7+$E$7)))) | E39: =IF(D39="","",IF(B39="","",IF(A39="","",IF($B$7="","",(D39*B39))))) | K39: =IFERROR(CONCATENATE(Tabela3[[#This Row],[INSTITUICAO]]," ",Tabela3[[#This Row],[TIPO OPERACAO]]," ",Tabela3[[#This Row],[TIPO INSTITUICAO]])," ") -> ONIX BOLETO FIDC | L39: ONIX | M39: BOLETO | N39: FIDC | O39: 0.025
C40: =IF(A40="","",A40-$B$7) | D40: =IF(A40="","",IF($B$7="","",IF(OR(WEEKDAY(A40)=5,WEEKDAY(A40)=6,WEEKDAY(A40)=7),A40-$B$7+$E$7+2,IF(WEEKDAY(A40)=1,A40-$B$7+$E$7+1,A40-$B$7+$E$7)))) | E40: =IF(D40="","",IF(B40="","",IF(A40="","",IF($B$7="","",(D40*B40))))) | K40: =IFERROR(CONCATENATE(Tabela3[[#This Row],[INSTITUICAO]]," ",Tabela3[[#This Row],[TIPO OPERACAO]]," ",Tabela3[[#This Row],[TIPO INSTITUICAO]])," ") -> SOMA FOMENTO FIDC | L40: SOMA | M40: FOMENTO | N40: FIDC | O40: 0.029
C41: =IF(A41="","",A41-$B$7) | D41: =IF(A41="","",IF($B$7="","",IF(OR(WEEKDAY(A41)=5,WEEKDAY(A41)=6,WEEKDAY(A41)=7),A41-$B$7+$E$7+2,IF(WEEKDAY(A41)=1,A41-$B$7+$E$7+1,A41-$B$7+$E$7)))) | E41: =IF(D41="","",IF(B41="","",IF(A41="","",IF($B$7="","",(D41*B41))))) | K41: =IFERROR(CONCATENATE(Tabela3[[#This Row],[INSTITUICAO]]," ",Tabela3[[#This Row],[TIPO OPERACAO]]," ",Tabela3[[#This Row],[TIPO INSTITUICAO]])," ") -> GFM BOLETO FIDC | L41: GFM | M41: BOLETO | N41: FIDC | O41: 0.025
C42: =IF(A42="","",A42-$B$7) | D42: =IF(A42="","",IF($B$7="","",IF(OR(WEEKDAY(A42)=5,WEEKDAY(A42)=6,WEEKDAY(A42)=7),A42-$B$7+$E$7+2,IF(WEEKDAY(A42)=1,A42-$B$7+$E$7+1,A42-$B$7+$E$7)))) | E42: =IF(D42="","",IF(B42="","",IF(A42="","",IF($B$7="","",(D42*B42))))) | K42: =IFERROR(CONCATENATE(Tabela3[[#This Row],[INSTITUICAO]]," ",Tabela3[[#This Row],[TIPO OPERACAO]]," ",Tabela3[[#This Row],[TIPO INSTITUICAO]])," ") -> GFM CHEQUE FIDC | L42: GFM | M42: CHEQUE | N42: FIDC | O42: 0.025
C43: =IF(A43="","",A43-$B$7) | D43: =IF(A43="","",IF($B$7="","",IF(OR(WEEKDAY(A43)=5,WEEKDAY(A43)=6,WEEKDAY(A43)=7),A43-$B$7+$E$7+2,IF(WEEKDAY(A43)=1,A43-$B$7+$E$7+1,A43-$B$7+$E$7)))) | E43: =IF(D43="","",IF(B43="","",IF(A43="","",IF($B$7="","",(D43*B43))))) | K43: =IFERROR(CONCATENATE(Tabela3[[#This Row],[INSTITUICAO]]," ",Tabela3[[#This Row],[TIPO OPERACAO]]," ",Tabela3[[#This Row],[TIPO INSTITUICAO]])," ") -> GFM FOMENTO FIDC | L43: GFM | M43: FOMENTO | N43: FIDC | O43: 0.03
C44: =IF(A44="","",A44-$B$7) | D44: =IF(A44="","",IF($B$7="","",IF(OR(WEEKDAY(A44)=5,WEEKDAY(A44)=6,WEEKDAY(A44)=7),A44-$B$7+$E$7+2,IF(WEEKDAY(A44)=1,A44-$B$7+$E$7+1,A44-$B$7+$E$7)))) | E44: =IF(D44="","",IF(B44="","",IF(A44="","",IF($B$7="","",(D44*B44))))) | K44: =IFERROR(CONCATENATE(Tabela3[[#This Row],[INSTITUICAO]]," ",Tabela3[[#This Row],[TIPO OPERACAO]]," ",Tabela3[[#This Row],[TIPO INSTITUICAO]])," ") -> CLIENTE BOLETO FIDC | L44: CLIENTE | M44: BOLETO | N44: FIDC | O44: 0.025
C45: =IF(A45="","",A45-$B$7) | D45: =IF(A45="","",IF($B$7="","",IF(OR(WEEKDAY(A45)=5,WEEKDAY(A45)=6,WEEKDAY(A45)=7),A45-$B$7+$E$7+2,IF(WEEKDAY(A45)=1,A45-$B$7+$E$7+1,A45-$B$7+$E$7)))) | E45: =IF(D45="","",IF(B45="","",IF(A45="","",IF($B$7="","",(D45*B45))))) | K45: =IFERROR(CONCATENATE(Tabela3[[#This Row],[INSTITUICAO]]," ",Tabela3[[#This Row],[TIPO OPERACAO]]," ",Tabela3[[#This Row],[TIPO INSTITUICAO]])," ") -> LOTUS CHEQUE FIDC | L45: LOTUS | M45: CHEQUE | N45: FIDC | O45: 0.018
... C49: =IF(A49="","",A49-$B$7) | D49: =IF(A49="","",IF($B$7="","",IF(OR(WEEKDAY(A49)=5,WEEKDAY(A49)=6,WEEKDAY(A49)=7),A49-$B$7+$E$7+2,IF(WEEKDAY(A49)=1,A49-$B$7+$E$7+1,A49-$B$7+$E$7)))) | E49: =IF(D49="","",IF(B49="","",IF(A49="","",IF($B$7="","",(D49*B49))))) | K49: =IFERROR(CONCATENATE(Tabela3[[#This Row],[INSTITUICAO]]," ",Tabela3[[#This Row],[TIPO OPERACAO]]," ",Tabela3[[#This Row],[TIPO INSTITUICAO]])," ") -> RSS FOMENTO SEC | L49: RSS | M49: FOMENTO | N49: SEC | O49: 0.029
C50: =IF(A50="","",A50-$B$7) | D50: =IF(A50="","",IF($B$7="","",IF(OR(WEEKDAY(A50)=5,WEEKDAY(A50)=6,WEEKDAY(A50)=7),A50-$B$7+$E$7+2,IF(WEEKDAY(A50)=1,A50-$B$7+$E$7+1,A50-$B$7+$E$7)))) | E50: =IF(D50="","",IF(B50="","",IF(A50="","",IF($B$7="","",(D50*B50))))) | K50: =IFERROR(CONCATENATE(Tabela3[[#This Row],[INSTITUICAO]]," ",Tabela3[[#This Row],[TIPO OPERACAO]]," ",Tabela3[[#This Row],[TIPO INSTITUICAO]])," ") -> SIGMA CHEQUE FIDC | L50: SIGMA | M50: CHEQUE | N50: FIDC | O50: 0.02 | P50: 3.02 | Q50: 25 | R50: 100 | S50: 50 | T50: 20
C51: =IF(A51="","",A51-$B$7) | D51: =IF(A51="","",IF($B$7="","",IF(OR(WEEKDAY(A51)=5,WEEKDAY(A51)=6,WEEKDAY(A51)=7),A51-$B$7+$E$7+2,IF(WEEKDAY(A51)=1,A51-$B$7+$E$7+1,A51-$B$7+$E$7)))) | E51: =IF(D51="","",IF(B51="","",IF(A51="","",IF($B$7="","",(D51*B51))))) | K51: =IFERROR(CONCATENATE(Tabela3[[#This Row],[INSTITUICAO]]," ",Tabela3[[#This Row],[TIPO OPERACAO]]," ",Tabela3[[#This Row],[TIPO INSTITUICAO]])," ") -> RSS CHEQUE SEC | L51: RSS | M51: CHEQUE | N51: SEC | O51: 0.027
C52: =IF(A52="","",A52-$B$7) | D52: =IF(A52="","",IF($B$7="","",IF(OR(WEEKDAY(A52)=5,WEEKDAY(A52)=6,WEEKDAY(A52)=7),A52-$B$7+$E$7+2,IF(WEEKDAY(A52)=1,A52-$B$7+$E$7+1,A52-$B$7+$E$7)))) | E52: =IF(D52="","",IF(B52="","",IF(A52="","",IF($B$7="","",(D52*B52))))) | K52: =IFERROR(CONCATENATE(Tabela3[[#This Row],[INSTITUICAO]]," ",Tabela3[[#This Row],[TIPO OPERACAO]]," ",Tabela3[[#This Row],[TIPO INSTITUICAO]])," ") -> REAL TIME COMISSARIA FIDC | L52: REAL TIME | M52: COMISSARIA | N52: FIDC | O52: 0.03
C53: =IF(A53="","",A53-$B$7) | D53: =IF(A53="","",IF($B$7="","",IF(OR(WEEKDAY(A53)=5,WEEKDAY(A53)=6,WEEKDAY(A53)=7),A53-$B$7+$E$7+2,IF(WEEKDAY(A53)=1,A53-$B$7+$E$7+1,A53-$B$7+$E$7)))) | E53: =IF(D53="","",IF(B53="","",IF(A53="","",IF($B$7="","",(D53*B53))))) | K53: =IFERROR(CONCATENATE(Tabela3[[#This Row],[INSTITUICAO]]," ",Tabela3[[#This Row],[TIPO OPERACAO]]," ",Tabela3[[#This Row],[TIPO INSTITUICAO]])," ") -> ONIX FOMENTO FIDC | L53: ONIX | M53: FOMENTO | N53: FIDC | O53: 0.03
C54: =IF(A54="","",A54-$B$7) | D54: =IF(A54="","",IF($B$7="","",IF(OR(WEEKDAY(A54)=5,WEEKDAY(A54)=6,WEEKDAY(A54)=7),A54-$B$7+$E$7+2,IF(WEEKDAY(A54)=1,A54-$B$7+$E$7+1,A54-$B$7+$E$7)))) | E54: =IF(D54="","",IF(B54="","",IF(A54="","",IF($B$7="","",(D54*B54))))) | K54: =IFERROR(CONCATENATE(Tabela3[[#This Row],[INSTITUICAO]]," ",Tabela3[[#This Row],[TIPO OPERACAO]]," ",Tabela3[[#This Row],[TIPO INSTITUICAO]])," ") -> BANICRED FOMENTO FIDC | L54: BANICRED | M54: FOMENTO | N54: FIDC | O54: 0.03
C55: =IF(A55="","",A55-$B$7) | D55: =IF(A55="","",IF($B$7="","",IF(OR(WEEKDAY(A55)=5,WEEKDAY(A55)=6,WEEKDAY(A55)=7),A55-$B$7+$E$7+2,IF(WEEKDAY(A55)=1,A55-$B$7+$E$7+1,A55-$B$7+$E$7)))) | E55: =IF(D55="","",IF(B55="","",IF(A55="","",IF($B$7="","",(D55*B55))))) | K55: =IFERROR(CONCATENATE(Tabela3[[#This Row],[INSTITUICAO]]," ",Tabela3[[#This Row],[TIPO OPERACAO]]," ",Tabela3[[#This Row],[TIPO INSTITUICAO]])," ") -> REAL TIME BOLETO FIDC | L55: REAL TIME | M55: BOLETO | N55: FIDC | O55: 0.025
C56: =IF(A56="","",A56-$B$7) | D56: =IF(A56="","",IF($B$7="","",IF(OR(WEEKDAY(A56)=5,WEEKDAY(A56)=6,WEEKDAY(A56)=7),A56-$B$7+$E$7+2,IF(WEEKDAY(A56)=1,A56-$B$7+$E$7+1,A56-$B$7+$E$7)))) | E56: =IF(D56="","",IF(B56="","",IF(A56="","",IF($B$7="","",(D56*B56))))) | K56: =IFERROR(CONCATENATE(Tabela3[[#This Row],[INSTITUICAO]]," ",Tabela3[[#This Row],[TIPO OPERACAO]]," ",Tabela3[[#This Row],[TIPO INSTITUICAO]])," ") -> BLACKBIRD FOMENTO SEC | L56: BLACKBIRD | M56: FOMENTO | N56: SEC | O56: 0.03
C57: =IF(A57="","",A57-$B$7) | D57: =IF(A57="","",IF($B$7="","",IF(OR(WEEKDAY(A57)=5,WEEKDAY(A57)=6,WEEKDAY(A57)=7),A57-$B$7+$E$7+2,IF(WEEKDAY(A57)=1,A57-$B$7+$E$7+1,A57-$B$7+$E$7)))) | E57: =IF(D57="","",IF(B57="","",IF(A57="","",IF($B$7="","",(D57*B57))))) | K57: =IFERROR(CONCATENATE(Tabela3[[#This Row],[INSTITUICAO]]," ",Tabela3[[#This Row],[TIPO OPERACAO]]," ",Tabela3[[#This Row],[TIPO INSTITUICAO]])," ") -> BLACKBIRD BOLETO SEC | L57: BLACKBIRD | M57: BOLETO | N57: SEC | O57: 0.024
C58: =IF(A58="","",A58-$B$7) | D58: =IF(A58="","",IF($B$7="","",IF(OR(WEEKDAY(A58)=5,WEEKDAY(A58)=6,WEEKDAY(A58)=7),A58-$B$7+$E$7+2,IF(WEEKDAY(A58)=1,A58-$B$7+$E$7+1,A58-$B$7+$E$7)))) | E58: =IF(D58="","",IF(B58="","",IF(A58="","",IF($B$7="","",(D58*B58))))) | K58: =IFERROR(CONCATENATE(Tabela3[[#This Row],[INSTITUICAO]]," ",Tabela3[[#This Row],[TIPO OPERACAO]]," ",Tabela3[[#This Row],[TIPO INSTITUICAO]])," ") -> SIGMA FOMENTO FIDC | L58: SIGMA | M58: FOMENTO | N58: FIDC | O58: 0.03
C59: =IF(A59="","",A59-$B$7) | D59: =IF(A59="","",IF($B$7="","",IF(OR(WEEKDAY(A59)=5,WEEKDAY(A59)=6,WEEKDAY(A59)=7),A59-$B$7+$E$7+2,IF(WEEKDAY(A59)=1,A59-$B$7+$E$7+1,A59-$B$7+$E$7)))) | E59: =IF(D59="","",IF(B59="","",IF(A59="","",IF($B$7="","",(D59*B59))))) | K59: =IFERROR(CONCATENATE(Tabela3[[#This Row],[INSTITUICAO]]," ",Tabela3[[#This Row],[TIPO OPERACAO]]," ",Tabela3[[#This Row],[TIPO INSTITUICAO]])," ") -> SIGMA BOLETO FIDC | L59: SIGMA | M59: BOLETO | N59: FIDC | O59: 0.02
C60: =IF(A60="","",A60-$B$7) | D60: =IF(A60="","",IF($B$7="","",IF(OR(WEEKDAY(A60)=5,WEEKDAY(A60)=6,WEEKDAY(A60)=7),A60-$B$7+$E$7+2,IF(WEEKDAY(A60)=1,A60-$B$7+$E$7+1,A60-$B$7+$E$7)))) | E60: =IF(D60="","",IF(B60="","",IF(A60="","",IF($B$7="","",(D60*B60))))) | K60: =IFERROR(CONCATENATE(Tabela3[[#This Row],[INSTITUICAO]]," ",Tabela3[[#This Row],[TIPO OPERACAO]]," ",Tabela3[[#This Row],[TIPO INSTITUICAO]])," ") -> ONIX COMISSARIA FIDC | L60: ONIX | M60: COMISSARIA | N60: FIDC | O60: 0.031
C61: =IF(A61="","",A61-$B$7) | D61: =IF(A61="","",IF($B$7="","",IF(OR(WEEKDAY(A61)=5,WEEKDAY(A61)=6,WEEKDAY(A61)=7),A61-$B$7+$E$7+2,IF(WEEKDAY(A61)=1,A61-$B$7+$E$7+1,A61-$B$7+$E$7)))) | E61: =IF(D61="","",IF(B61="","",IF(A61="","",IF($B$7="","",(D61*B61))))) | K61: =IFERROR(CONCATENATE(Tabela3[[#This Row],[INSTITUICAO]]," ",Tabela3[[#This Row],[TIPO OPERACAO]]," ",Tabela3[[#This Row],[TIPO INSTITUICAO]])," ") -> LOTUS FOMENTO FIDC | L61: LOTUS | M61: FOMENTO | N61: FIDC | O61: 0.029
C62: =IF(A62="","",A62-$B$7) | D62: =IF(A62="","",IF($B$7="","",IF(OR(WEEKDAY(A62)=5,WEEKDAY(A62)=6,WEEKDAY(A62)=7),A62-$B$7+$E$7+2,IF(WEEKDAY(A62)=1,A62-$B$7+$E$7+1,A62-$B$7+$E$7)))) | E62: =IF(D62="","",IF(B62="","",IF(A62="","",IF($B$7="","",(D62*B62))))) | K62: =IFERROR(CONCATENATE(Tabela3[[#This Row],[INSTITUICAO]]," ",Tabela3[[#This Row],[TIPO OPERACAO]]," ",Tabela3[[#This Row],[TIPO INSTITUICAO]])," ") -> ERM COMISSARIA PF | L62: ERM | M62: COMISSARIA | N62: PF | O62: 0.032
... C73: =IF(A73="","",A73-$B$7) | D73: =IF(A73="","",IF($B$7="","",IF(OR(WEEKDAY(A73)=5,WEEKDAY(A73)=6,WEEKDAY(A73)=7),A73-$B$7+$E$7+2,IF(WEEKDAY(A73)=1,A73-$B$7+$E$7+1,A73-$B$7+$E$7)))) | E73: =IF(D73="","",IF(B73="","",IF(A73="","",IF($B$7="","",(D73*B73))))) | K73: =IFERROR(CONCATENATE(Tabela3[[#This Row],[INSTITUICAO]]," ",Tabela3[[#This Row],[TIPO OPERACAO]]," ",Tabela3[[#This Row],[TIPO INSTITUICAO]])," ") -> BRR FOMENTO FIDC | L73: BRR | M73: FOMENTO | N73: FIDC | O73: 0.03
C74: =IF(A74="","",A74-$B$7) | D74: =IF(A74="","",IF($B$7="","",IF(OR(WEEKDAY(A74)=5,WEEKDAY(A74)=6,WEEKDAY(A74)=7),A74-$B$7+$E$7+2,IF(WEEKDAY(A74)=1,A74-$B$7+$E$7+1,A74-$B$7+$E$7)))) | E74: =IF(D74="","",IF(B74="","",IF(A74="","",IF($B$7="","",(D74*B74))))) | K74: =IFERROR(CONCATENATE(Tabela3[[#This Row],[INSTITUICAO]]," ",Tabela3[[#This Row],[TIPO OPERACAO]]," ",Tabela3[[#This Row],[TIPO INSTITUICAO]])," ") -> BRR CHEQUE FIDC | L74: BRR | M74: CHEQUE | N74: FIDC | O74: 0.022 | Q74: 20 | U74: 50
C75: =IF(A75="","",A75-$B$7) | D75: =IF(A75="","",IF($B$7="","",IF(OR(WEEKDAY(A75)=5,WEEKDAY(A75)=6,WEEKDAY(A75)=7),A75-$B$7+$E$7+2,IF(WEEKDAY(A75)=1,A75-$B$7+$E$7+1,A75-$B$7+$E$7)))) | E75: =IF(D75="","",IF(B75="","",IF(A75="","",IF($B$7="","",(D75*B75))))) | K75: =IFERROR(CONCATENATE(Tabela3[[#This Row],[INSTITUICAO]]," ",Tabela3[[#This Row],[TIPO OPERACAO]]," ",Tabela3[[#This Row],[TIPO INSTITUICAO]])," ") -> BRR BOLETO FIDC | L75: BRR | M75: BOLETO | N75: FIDC | O75: 0.021
C76: =IF(A76="","",A76-$B$7) | D76: =IF(A76="","",IF($B$7="","",IF(OR(WEEKDAY(A76)=5,WEEKDAY(A76)=6,WEEKDAY(A76)=7),A76-$B$7+$E$7+2,IF(WEEKDAY(A76)=1,A76-$B$7+$E$7+1,A76-$B$7+$E$7)))) | E76: =IF(D76="","",IF(B76="","",IF(A76="","",IF($B$7="","",(D76*B76))))) | K76: =IFERROR(CONCATENATE(Tabela3[[#This Row],[INSTITUICAO]]," ",Tabela3[[#This Row],[TIPO OPERACAO]]," ",Tabela3[[#This Row],[TIPO INSTITUICAO]])," ") -> BLACKBIRD BOLETO FIDC | L76: BLACKBIRD | M76: BOLETO | N76: FIDC | O76: 0.025
C77: =IF(A77="","",A77-$B$7) | D77: =IF(A77="","",IF($B$7="","",IF(OR(WEEKDAY(A77)=5,WEEKDAY(A77)=6,WEEKDAY(A77)=7),A77-$B$7+$E$7+2,IF(WEEKDAY(A77)=1,A77-$B$7+$E$7+1,A77-$B$7+$E$7)))) | E77: =IF(D77="","",IF(B77="","",IF(A77="","",IF($B$7="","",(D77*B77))))) | K77: =IFERROR(CONCATENATE(Tabela3[[#This Row],[INSTITUICAO]]," ",Tabela3[[#This Row],[TIPO OPERACAO]]," ",Tabela3[[#This Row],[TIPO INSTITUICAO]])," ") -> IRMAOS BOA RISCO SACADO RSC | L77: IRMAOS BOA | M77: RISCO SACADO | N77: RSC | O77: 0.025
C78: =IF(A78="","",A78-$B$7) | D78: =IF(A78="","",IF($B$7="","",IF(OR(WEEKDAY(A78)=5,WEEKDAY(A78)=6,WEEKDAY(A78)=7),A78-$B$7+$E$7+2,IF(WEEKDAY(A78)=1,A78-$B$7+$E$7+1,A78-$B$7+$E$7)))) | E78: =IF(D78="","",IF(B78="","",IF(A78="","",IF($B$7="","",(D78*B78))))) | K78: =IFERROR(CONCATENATE(Tabela3[[#This Row],[INSTITUICAO]]," ",Tabela3[[#This Row],[TIPO OPERACAO]]," ",Tabela3[[#This Row],[TIPO INSTITUICAO]])," ") -> HERCULES CHEQUE FIDC | L78: HERCULES | M78: CHEQUE | N78: FIDC | O78: 0.0185
C79: =IF(A79="","",A79-$B$7) | D79: =IF(A79="","",IF($B$7="","",IF(OR(WEEKDAY(A79)=5,WEEKDAY(A79)=6,WEEKDAY(A79)=7),A79-$B$7+$E$7+2,IF(WEEKDAY(A79)=1,A79-$B$7+$E$7+1,A79-$B$7+$E$7)))) | E79: =IF(D79="","",IF(B79="","",IF(A79="","",IF($B$7="","",(D79*B79))))) | K79: =IFERROR(CONCATENATE(Tabela3[[#This Row],[INSTITUICAO]]," ",Tabela3[[#This Row],[TIPO OPERACAO]]," ",Tabela3[[#This Row],[TIPO INSTITUICAO]])," ") -> BRR BOLETO ESPECIAL FIDC | L79: BRR | M79: BOLETO ESPECIAL | N79: FIDC | O79: 0.025
C80: =IF(A80="","",A80-$B$7) | D80: =IF(A80="","",IF($B$7="","",IF(OR(WEEKDAY(A80)=5,WEEKDAY(A80)=6,WEEKDAY(A80)=7),A80-$B$7+$E$7+2,IF(WEEKDAY(A80)=1,A80-$B$7+$E$7+1,A80-$B$7+$E$7)))) | E80: =IF(D80="","",IF(B80="","",IF(A80="","",IF($B$7="","",(D80*B80))))) | K80: =IFERROR(CONCATENATE(Tabela3[[#This Row],[INSTITUICAO]]," ",Tabela3[[#This Row],[TIPO OPERACAO]]," ",Tabela3[[#This Row],[TIPO INSTITUICAO]])," ") -> NOBEL BOLETO ESPECIAL FIDC | L80: NOBEL | M80: BOLETO ESPECIAL | N80: FIDC | O80: 0.022
C81: =IF(A81="","",A81-$B$7) | D81: =IF(A81="","",IF($B$7="","",IF(OR(WEEKDAY(A81)=5,WEEKDAY(A81)=6,WEEKDAY(A81)=7),A81-$B$7+$E$7+2,IF(WEEKDAY(A81)=1,A81-$B$7+$E$7+1,A81-$B$7+$E$7)))) | E81: =IF(D81="","",IF(B81="","",IF(A81="","",IF($B$7="","",(D81*B81))))) | K81: =IFERROR(CONCATENATE(Tabela3[[#This Row],[INSTITUICAO]]," ",Tabela3[[#This Row],[TIPO OPERACAO]]," ",Tabela3[[#This Row],[TIPO INSTITUICAO]])," ") -> GOAL BOLETO ESPECIAL FIDC | L81: GOAL | M81: BOLETO ESPECIAL | N81: FIDC | O81: 0.022
C82: =IF(A82="","",A82-$B$7) | D82: =IF(A82="","",IF($B$7="","",IF(OR(WEEKDAY(A82)=5,WEEKDAY(A82)=6,WEEKDAY(A82)=7),A82-$B$7+$E$7+2,IF(WEEKDAY(A82)=1,A82-$B$7+$E$7+1,A82-$B$7+$E$7)))) | E82: =IF(D82="","",IF(B82="","",IF(A82="","",IF($B$7="","",(D82*B82))))) | K82: =IFERROR(CONCATENATE(Tabela3[[#This Row],[INSTITUICAO]]," ",Tabela3[[#This Row],[TIPO OPERACAO]]," ",Tabela3[[#This Row],[TIPO INSTITUICAO]])," ") -> ATIVA BOLETO ESPECIAL FIDC | L82: ATIVA | M82: BOLETO ESPECIAL | N82: FIDC | O82: 0.0245
C83: =IF(A83="","",A83-$B$7) | D83: =IF(A83="","",IF($B$7="","",IF(OR(WEEKDAY(A83)=5,WEEKDAY(A83)=6,WEEKDAY(A83)=7),A83-$B$7+$E$7+2,IF(WEEKDAY(A83)=1,A83-$B$7+$E$7+1,A83-$B$7+$E$7)))) | E83: =IF(D83="","",IF(B83="","",IF(A83="","",IF($B$7="","",(D83*B83))))) | K83: =IFERROR(CONCATENATE(Tabela3[[#This Row],[INSTITUICAO]]," ",Tabela3[[#This Row],[TIPO OPERACAO]]," ",Tabela3[[#This Row],[TIPO INSTITUICAO]])," ") -> LEPTA BOLETO ESPECIAL FIDC | L83: LEPTA | M83: BOLETO ESPECIAL | N83: FIDC | O83: 0.029
C84: =IF(A84="","",A84-$B$7) | D84: =IF(A84="","",IF($B$7="","",IF(OR(WEEKDAY(A84)=5,WEEKDAY(A84)=6,WEEKDAY(A84)=7),A84-$B$7+$E$7+2,IF(WEEKDAY(A84)=1,A84-$B$7+$E$7+1,A84-$B$7+$E$7)))) | E84: =IF(D84="","",IF(B84="","",IF(A84="","",IF($B$7="","",(D84*B84))))) | K84: =IFERROR(CONCATENATE(Tabela3[[#This Row],[INSTITUICAO]]," ",Tabela3[[#This Row],[TIPO OPERACAO]]," ",Tabela3[[#This Row],[TIPO INSTITUICAO]])," ") -> ATIVA BOLETO FIDC | L84: ATIVA | M84: BOLETO | N84: FIDC | O84: 0.022
C85: =IF(A85="","",A85-$B$7) | D85: =IF(A85="","",IF($B$7="","",IF(OR(WEEKDAY(A85)=5,WEEKDAY(A85)=6,WEEKDAY(A85)=7),A85-$B$7+$E$7+2,IF(WEEKDAY(A85)=1,A85-$B$7+$E$7+1,A85-$B$7+$E$7)))) | E85: =IF(D85="","",IF(B85="","",IF(A85="","",IF($B$7="","",(D85*B85))))) | K85: =IFERROR(CONCATENATE(Tabela3[[#This Row],[INSTITUICAO]]," ",Tabela3[[#This Row],[TIPO OPERACAO]]," ",Tabela3[[#This Row],[TIPO INSTITUICAO]])," ") -> DÍNAMO BOLETO FIDC | L85: DÍNAMO | M85: BOLETO | N85: FIDC | O85: 0.022
C86: =IF(A86="","",A86-$B$7) | D86: =IF(A86="","",IF($B$7="","",IF(OR(WEEKDAY(A86)=5,WEEKDAY(A86)=6,WEEKDAY(A86)=7),A86-$B$7+$E$7+2,IF(WEEKDAY(A86)=1,A86-$B$7+$E$7+1,A86-$B$7+$E$7)))) | E86: =IF(D86="","",IF(B86="","",IF(A86="","",IF($B$7="","",(D86*B86))))) | K86: =IFERROR(CONCATENATE(Tabela3[[#This Row],[INSTITUICAO]]," ",Tabela3[[#This Row],[TIPO OPERACAO]]," ",Tabela3[[#This Row],[TIPO INSTITUICAO]])," ") -> VALECRED FOMENTO FIDC | L86: VALECRED | M86: FOMENTO | N86: FIDC | O86: 0.027
... C89: =IF(A89="","",A89-$B$7) | D89: =IF(A89="","",IF($B$7="","",IF(OR(WEEKDAY(A89)=5,WEEKDAY(A89)=6,WEEKDAY(A89)=7),A89-$B$7+$E$7+2,IF(WEEKDAY(A89)=1,A89-$B$7+$E$7+1,A89-$B$7+$E$7)))) | E89: =IF(D89="","",IF(B89="","",IF(A89="","",IF($B$7="","",(D89*B89))))) | K89: =IFERROR(CONCATENATE(Tabela3[[#This Row],[INSTITUICAO]]," ",Tabela3[[#This Row],[TIPO OPERACAO]]," ",Tabela3[[#This Row],[TIPO INSTITUICAO]])," ") -> VALE RIO CLARO BOLETO FIDC | L89: VALE RIO CLARO | M89: BOLETO | N89: FIDC | O89: 0.024
C90: =IF(A90="","",A90-$B$7) | D90: =IF(A90="","",IF($B$7="","",IF(OR(WEEKDAY(A90)=5,WEEKDAY(A90)=6,WEEKDAY(A90)=7),A90-$B$7+$E$7+2,IF(WEEKDAY(A90)=1,A90-$B$7+$E$7+1,A90-$B$7+$E$7)))) | E90: =IF(D90="","",IF(B90="","",IF(A90="","",IF($B$7="","",(D90*B90)))))

Sheet TD
C6: Soma de VALOR P | D6: Rótulos de Coluna
C7: Rótulos de Linha | D7: A VENCER | E7: VENCIDO | F7: LIQUIDADO | G7: Total Geral
C8: jan | E8: 112497.11 | F8: 664663.25 | G8: 777160.36
C9: fev | D9: 1524845.2 | G9: 1524845.2
C10: mar | D10: 599437.1 | G10: 599437.1
C11: abr | D11: 150643.09 | G11: 150643.09
C12: mai | D12: 46650.28 | G12: 46650.28
C13: dez | E13: 5875 | F13: 1568.69 | G13: 7443.69
C14: Total Geral | D14: 2321575.6 | E14: 118372.11 | F14: 666231.94 | G14: 3106179.7
